Workbook

Sheet Leia-me
A1: Painel ClimaBrasil — Base de Dados Tratada
A2: Reconstrução e organização da base bruta 'pcb-raw-data' (TCU / ClimateScanner)
A5: O QUE FOI FEITO
A6: O arquivo original continha o CSV bruto do Painel ClimaBrasil colado em uma única coluna do Excel. Como vários
A7: comentários de auditores possuem quebras de linha dentro de campos entre aspas, o Excel havia fragmentado cada
A8: parágrafo em uma linha própria da planilha (5.399 linhas para o que deveriam ser ~1.400 registros). Os dados foram
A9: reconstruídos a partir do texto bruto, identificando o início de cada avaliação por seu padrão fixo de campos
A10: (id, eixo, data, versão, tipo de ente, nome, id do ente, componente, item, nota), separando corretamente cada
A11: registro em uma linha e preservando o comentário completo do auditor.
A13: ESTRUTURA DOS DADOS
A14: • 1.398 avaliações (1 linha = 1 item avaliado em 1 ente federativo)
A15: • 48 entes avaliados nesta base: estados/DF e capitais
... A39: Em 5 células de comentário (Amazonas G3-A, G4-C, G5-A, G6-C; Vitória G7-C), o texto contém a marca literal '#NAME?'. Isso já estava presente no arquivo original enviado (confirmado: 45 ocorrências no arquivo-fonte) — provavelmente um trecho iniciado por hífen foi interpretado como fórmula em uma edição anterior do arquivo e o conteúdo original não pôde ser recuperado. Não é um erro introduzido neste tratamento.

Sheet Resumo por Ente
A1: Tipo de Ente | B1: Nome do Ente | C1: Nº de Registros | D1: Itens com Nota Válida | E1: Nota Média Geral | F1: Nota Média — Governança | G1: Nota Média — Financiamento
A2: Estado | B2: Acre | C2: =COUNTIF(Dados!$G:$G,B2) -> 28 | D2: =COUNTIFS(Dados!$G:$G,B2,Dados!$M:$M,"<>") -> 28 | E2: =IFERROR(AVERAGEIFS(Dados!$M:$M,Dados!$G:$G,B2),"") -> 0.76160714 | F2: =IFERROR(AVERAGEIFS(Dados!$M:$M,Dados!$G:$G,B2,Dados!$B:$B,"Governança"),"") -> 0.85936842 | G2: =IFERROR(AVERAGEIFS(Dados!$M:$M,Dados!$G:$G,B2,Dados!$B:$B,"Financiamento"),"") -> 0.55522222
A3: Estado | B3: Alagoas | C3: =COUNTIF(Dados!$G:$G,B3) -> 28 | D3: =COUNTIFS(Dados!$G:$G,B3,Dados!$M:$M,"<>") -> 28 | E3: =IFERROR(AVERAGEIFS(Dados!$M:$M,Dados!$G:$G,B3),"") -> 0.51164286 | F3: =IFERROR(AVERAGEIFS(Dados!$M:$M,Dados!$G:$G,B3,Dados!$B:$B,"Governança"),"") -> 0.59615789 | G3: =IFERROR(AVERAGEIFS(Dados!$M:$M,Dados!$G:$G,B3,Dados!$B:$B,"Financiamento"),"") -> 0.33322222
A4: Estado | B4: Amapá | C4: =COUNTIF(Dados!$G:$G,B4) -> 28 | D4: =COUNTIFS(Dados!$G:$G,B4,Dados!$M:$M,"<>") -> 28 | E4: =IFERROR(AVERAGEIFS(Dados!$M:$M,Dados!$G:$G,B4),"") -> 0.48764286 | F4: =IFERROR(AVERAGEIFS(Dados!$M:$M,Dados!$G:$G,B4,Dados!$B:$B,"Governança"),"") -> 0.56089474 | G4: =IFERROR(AVERAGEIFS(Dados!$M:$M,Dados!$G:$G,B4,Dados!$B:$B,"Financiamento"),"") -> 0.333
A5: Estado | B5: Amazonas | C5: =COUNTIF(Dados!$G:$G,B5) -> 28 | D5: =COUNTIFS(Dados!$G:$G,B5,Dados!$M:$M,"<>") -> 28 | E5: =IFERROR(AVERAGEIFS(Dados!$M:$M,Dados!$G:$G,B5),"") -> 0.39253571 | F5: =IFERROR(AVERAGEIFS(Dados!$M:$M,Dados!$G:$G,B5,Dados!$B:$B,"Governança"),"") -> 0.45578947 | G5: =IFERROR(AVERAGEIFS(Dados!$M:$M,Dados!$G:$G,B5,Dados!$B:$B,"Financiamento"),"") -> 0.259
A6: Estado | B6: Bahia | C6: =COUNTIF(Dados!$G:$G,B6) -> 28 | D6: =COUNTIFS(Dados!$G:$G,B6,Dados!$M:$M,"<>") -> 28 | E6: =IFERROR(AVERAGEIFS(Dados!$M:$M,Dados!$G:$G,B6),"") -> 0.52353571 | F6: =IFERROR(AVERAGEIFS(Dados!$M:$M,Dados!$G:$G,B6,Dados!$B:$B,"Governança"),"") -> 0.63131579 | G6: =IFERROR(AVERAGEIFS(Dados!$M:$M,Dados!$G:$G,B6,Dados!$B:$B,"Financiamento"),"") -> 0.296
A7: Estado | B7: Ceará | C7: =COUNTIF(Dados!$G:$G,B7) -> 28 | D7: =COUNTIFS(Dados!$G:$G,B7,Dados!$M:$M,"<>") -> 28 | E7: =IFERROR(AVERAGEIFS(Dados!$M:$M,Dados!$G:$G,B7),"") -> 0.63064286 | F7: =IFERROR(AVERAGEIFS(Dados!$M:$M,Dados!$G:$G,B7,Dados!$B:$B,"Governança"),"") -> 0.73652632 | G7: =IFERROR(AVERAGEIFS(Dados!$M:$M,Dados!$G:$G,B7,Dados!$B:$B,"Financiamento"),"") -> 0.40711111
A8: Estado | B8: Espírito Santo | C8: =COUNTIF(Dados!$G:$G,B8) -> 28 | D8: =COUNTIFS(Dados!$G:$G,B8,Dados!$M:$M,"<>") -> 28 | E8: =IFERROR(AVERAGEIFS(Dados!$M:$M,Dados!$G:$G,B8),"") -> 0.42825 | F8: =IFERROR(AVERAGEIFS(Dados!$M:$M,Dados!$G:$G,B8,Dados!$B:$B,"Governança"),"") -> 0.47336842 | G8: =IFERROR(AVERAGEIFS(Dados!$M:$M,Dados!$G:$G,B8,Dados!$B:$B,"Financiamento"),"") -> 0.333
A9: Estado | B9: Goiás | C9: =COUNTIF(Dados!$G:$G,B9) -> 28 | D9: =COUNTIFS(Dados!$G:$G,B9,Dados!$M:$M,"<>") -> 28 | E9: =IFERROR(AVERAGEIFS(Dados!$M:$M,Dados!$G:$G,B9),"") -> 0.54735714 | F9: =IFERROR(AVERAGEIFS(Dados!$M:$M,Dados!$G:$G,B9,Dados!$B:$B,"Governança"),"") -> 0.63126316 | G9: =IFERROR(AVERAGEIFS(Dados!$M:$M,Dados!$G:$G,B9,Dados!$B:$B,"Financiamento"),"") -> 0.37022222
A10: Estado | B10: Maranhão | C10: =COUNTIF(Dados!$G:$G,B10) -> 28 | D10: =COUNTIFS(Dados!$G:$G,B10,Dados!$M:$M,"<>") -> 28 | E10: =IFERROR(AVERAGEIFS(Dados!$M:$M,Dados!$G:$G,B10),"") -> 0.77367857 | F10: =IFERROR(AVERAGEIFS(Dados!$M:$M,Dados!$G:$G,B10,Dados!$B:$B,"Governança"),"") -> 0.89463158 | G10: =IFERROR(AVERAGEIFS(Dados!$M:$M,Dados!$G:$G,B10,Dados!$B:$B,"Financiamento"),"") -> 0.51833333
A11: Estado | B11: Mato Grosso | C11: =COUNTIF(Dados!$G:$G,B11) -> 28 | D11: =COUNTIFS(Dados!$G:$G,B11,Dados!$M:$M,"<>") -> 28 | E11: =IFERROR(AVERAGEIFS(Dados!$M:$M,Dados!$G:$G,B11),"") -> 0.59496429 | F11: =IFERROR(AVERAGEIFS(Dados!$M:$M,Dados!$G:$G,B11,Dados!$B:$B,"Governança"),"") -> 0.66642105 | G11: =IFERROR(AVERAGEIFS(Dados!$M:$M,Dados!$G:$G,B11,Dados!$B:$B,"Financiamento"),"") -> 0.44411111
A12: Estado | B12: Mato Grosso do Sul | C12: =COUNTIF(Dados!$G:$G,B12) -> 28 | D12: =COUNTIFS(Dados!$G:$G,B12,Dados!$M:$M,"<>") -> 28 | E12: =IFERROR(AVERAGEIFS(Dados!$M:$M,Dados!$G:$G,B12),"") -> 0.49975 | F12: =IFERROR(AVERAGEIFS(Dados!$M:$M,Dados!$G:$G,B12,Dados!$B:$B,"Governança"),"") -> 0.50847368 | G12: =IFERROR(AVERAGEIFS(Dados!$M:$M,Dados!$G:$G,B12,Dados!$B:$B,"Financiamento"),"") -> 0.48133333
A13: Estado | B13: Minas Gerais | C13: =COUNTIF(Dados!$G:$G,B13) -> 28 | D13: =COUNTIFS(Dados!$G:$G,B13,Dados!$M:$M,"<>") -> 28 | E13: =IFERROR(AVERAGEIFS(Dados!$M:$M,Dados!$G:$G,B13),"") -> 0.84496429 | F13: =IFERROR(AVERAGEIFS(Dados!$M:$M,Dados!$G:$G,B13,Dados!$B:$B,"Governança"),"") -> 0.87694737 | G13: =IFERROR(AVERAGEIFS(Dados!$M:$M,Dados!$G:$G,B13,Dados!$B:$B,"Financiamento"),"") -> 0.77744444
... A51: Município | B51: Vitória | C51: =COUNTIF(Dados!$G:$G,B51) -> 28 | D51: =COUNTIFS(Dados!$G:$G,B51,Dados!$M:$M,"<>") -> 28 | E51: =IFERROR(AVERAGEIFS(Dados!$M:$M,Dados!$G:$G,B51),"") -> 0.14088462 | F51: =IFERROR(AVERAGEIFS(Dados!$M:$M,Dados!$G:$G,B51,Dados!$B:$B,"Governança"),"") -> 0.11752941 | G51: =IFERROR(AVERAGEIFS(Dados!$M:$M,Dados!$G:$G,B51,Dados!$B:$B,"Financiamento"),"") -> 0.185

Sheet Resumo por Pilar
A1: Eixo | B1: Componente | C1: Pilar | D1: Nº de Registros | E1: Itens com Nota Válida | F1: Nota Média
A2: Financiamento | B2: F1 | C2: Finanças e gastos públicos | D2: =COUNTIF(Dados!$C:$C,B2) -> 200 | E2: =COUNTIFS(Dados!$C:$C,B2,Dados!$M:$M,"<>") -> 200 | F2: =IFERROR(AVERAGEIFS(Dados!$M:$M,Dados!$C:$C,B2),"") -> 0.33478
A3: Financiamento | B3: F2 | C3: Captação de recursos | D3: =COUNTIF(Dados!$C:$C,B3) -> 150 | E3: =COUNTIFS(Dados!$C:$C,B3,Dados!$M:$M,"<>") -> 150 | F3: =IFERROR(AVERAGEIFS(Dados!$M:$M,Dados!$C:$C,B3),"") -> 0.44043624
A4: Financiamento | B4: F3 | C4: Mobilização de investimento privado | D4: =COUNTIF(Dados!$C:$C,B4) -> 100 | E4: =COUNTIFS(Dados!$C:$C,B4,Dados!$M:$M,"<>") -> 100 | F4: =IFERROR(AVERAGEIFS(Dados!$M:$M,Dados!$C:$C,B4),"") -> 0.27871429
A5: Governança | B5: G1 | C5: Quadro legal | D5: =COUNTIF(Dados!$C:$C,B5) -> 150 | E5: =COUNTIFS(Dados!$C:$C,B5,Dados!$M:$M,"<>") -> 150 | F5: =IFERROR(AVERAGEIFS(Dados!$M:$M,Dados!$C:$C,B5),"") -> 0.67980667
A6: Governança | B6: G2 | C6: Estrutura governamental | D6: =COUNTIF(Dados!$C:$C,B6) -> 149 | E6: =COUNTIFS(Dados!$C:$C,B6,Dados!$M:$M,"<>") -> 149 | F6: =IFERROR(AVERAGEIFS(Dados!$M:$M,Dados!$C:$C,B6),"") -> 0.65963265
A7: Governança | B7: G3 | C7: Gestão de riscos | D7: =COUNTIF(Dados!$C:$C,B7) -> 99 | E7: =COUNTIFS(Dados!$C:$C,B7,Dados!$M:$M,"<>") -> 99 | F7: =IFERROR(AVERAGEIFS(Dados!$M:$M,Dados!$C:$C,B7),"") -> 0.50489691
A8: Governança | B8: G4 | C8: Coordenação horizontal e vertical | D8: =COUNTIF(Dados!$C:$C,B8) -> 150 | E8: =COUNTIFS(Dados!$C:$C,B8,Dados!$M:$M,"<>") -> 150 | F8: =IFERROR(AVERAGEIFS(Dados!$M:$M,Dados!$C:$C,B8),"") -> 0.64147619
A9: Governança | B9: G5 | C9: Engajamento de partes interessadas | D9: =COUNTIF(Dados!$C:$C,B9) -> 100 | E9: =COUNTIFS(Dados!$C:$C,B9,Dados!$M:$M,"<>") -> 100 | F9: =IFERROR(AVERAGEIFS(Dados!$M:$M,Dados!$C:$C,B9),"") -> 0.63628
A10: Governança | B10: G6 | C10: Justiça climática | D10: =COUNTIF(Dados!$C:$C,B10) -> 150 | E10: =COUNTIFS(Dados!$C:$C,B10,Dados!$M:$M,"<>") -> 150 | F10: =IFERROR(AVERAGEIFS(Dados!$M:$M,Dados!$C:$C,B10),"") -> 0.38037838
A11: Governança | B11: G7 | C11: Atuação do Legislativo, Judiciário e Controle | D11: =COUNTIF(Dados!$C:$C,B11) -> 150 | E11: =COUNTIFS(Dados!$C:$C,B11,Dados!$M:$M,"<>") -> 150 | F11: =IFERROR(AVERAGEIFS(Dados!$M:$M,Dados!$C:$C,B11),"") -> 0.46045528

Sheet Dados
A1: ID Avaliação | B1: Eixo | C1: Componente | D1: Pilar | E1: Item | F1: Tipo de Ente | G1: Nome do Ente | H1: ID do Ente | I1: Data da Avaliação | J1: Versão | K1: Nota (Texto) | L1: Nota (Valor Original) | M1: Nota Numérica (p/ médias) | N1: Comentário do Auditor | O1: Justificativa de Confidencialidade | P1: Status
A2: 7876 | B2: Financiamento | C2: F1 | D2: Finanças e gastos públicos | E2: A | F2: Estado | G2: Acre | H2: 12 | I2: 45912.645 | J2: Versão de Avaliação 2025 | K2: Estágio avançado | L2: 1 | M2: =IF(K2="Sem progresso",0,IF(OR(K2="Não avaliado",K2="Não se aplica",K2=""),"",L2)) -> 1 | N2: No PPA é previsto um programa Específico 1460- Programa Ecossistema de Inivação Ambiental e Adaptação Climática, com orçamento em 2024: R$ 10.521.086,24 e 2025: R$ 10.856.375,97. O Programa 1459 - Regularização, controle e monitoramento ambiental, prevê o orçamento de 2024: R$ 11.157.652,57 - 2025: R$ 11.513.228,62 e tem como objetivo Desenvolver de forma ampla o monitoramento ambiental do estado do Acre (cobertura florestal, hidrometeorológico, queimadas, qualidade do ar e a dinâmica de uso e ocupação do solo). Há também o programa Infraestrutura e mobilidade Urbana que prevê o orçamento de 2024: R$ 246.234.833,46 - 2025: R$ 254.081.932,93 e tem como OBJETIVO ESPECÍFICO 5: Implantação e Urbanização de Parques e OBJETIVO ESPECÍFICO 6:Preservação das Encostas de Rios e Igarapés Programa 1453 - Saneia Acre, com objetivo de Ampliar a oferta de rede de distribuição de água potável e da rede coletora e de tratamento de esgoto em todos municípios do Estado. Orçamento previsto: 2024: R$ 62.277.884,85 - 2025: R$ 64.262.578,69 | P2: P
A3: 7881 | B3: Financiamento | C3: F1 | D3: Finanças e gastos públicos | E3: B | F3: Estado | G3: Acre | H3: 12 | I3: 45912.645 | J3: Versão de Avaliação 2025 | K3: Estágio intermediário | L3: 0.666 | M3: =IF(K3="Sem progresso",0,IF(OR(K3="Não avaliado",K3="Não se aplica",K3=""),"",L3)) -> 0.666 | N3: No PPA é possível identificar programas com nomes relacionados ao clima, mas não um sistema de classificação em seu orçamento (Programa 1460 - Ecossistema de Inivação Ambiental e Adaptação Climática, em outros programas). Já na LOA 2025 pode-se identificar, mensurar e classificar gastos direcionados para ações climáticas, como por exemplo no Anexo 7 - Lei 2030: Código: 18.541.1460. Especificação: ECOSSISTEMA DE INOVAÇÃO AMBIENTAl e Adaptação Climática. Projetos: 15.225.268,48 Não foi possivel encontrar ações que possam contribuir negativamente para os objetivos climáticos. Porém a LOA 2025, | P3: P
A4: 7884 | B4: Financiamento | C4: F1 | D4: Finanças e gastos públicos | E4: C | F4: Estado | G4: Acre | H4: 12 | I4: 45912.645 | J4: Versão de Avaliação 2025 | K4: Sem progresso | M4: =IF(K4="Sem progresso",0,IF(OR(K4="Não avaliado",K4="Não se aplica",K4=""),"",L4)) -> 0 | N4: Em algumas licitações no Acre, documentos como o DOF e o licenciamento de operação são exigidos para comprovar a origem e legalidade de produtos florestais. Embora não haja menção específica a um "selo verde" do Acre, o estado tem algumas poucas ações de sustentabilidade, como o Prêmio Socioambiental Chico Mendes. Porém, não foi possível constatar que esta seja uma pratica institucionalizada do Estado em sua rotina de contratações e compras. | P4: P
A5: 7967 | B5: Financiamento | C5: F1 | D5: Finanças e gastos públicos | E5: D | F5: Estado | G5: Acre | H5: 12 | I5: 45912.645 | J5: Versão de Avaliação 2025 | K5: Estágio intermediário | L5: 0.666 | M5: =IF(K5="Sem progresso",0,IF(OR(K5="Não avaliado",K5="Não se aplica",K5=""),"",L5)) -> 0.666 | N5: "O portal de transparencia apresenta os dados orçamentários da gestão ambiental como um todo, não sendo possível discriminar os gastos em programas específicos. O acesso é feito pelo endereço www.acreppp.org, onde é possível encontrar de forma precisa indicadores de desmatamento - que registrou uma redução de 66% no período de 12 anos
A6: 7968 | B6: Financiamento | C6: F2 | D6: Captação de recursos | E6: A | F6: Estado | G6: Acre | H6: 12 | I6: 45912.645 | J6: Versão de Avaliação 2025 | K6: Estágio intermediário | L6: 0.666 | M6: =IF(K6="Sem progresso",0,IF(OR(K6="Não avaliado",K6="Não se aplica",K6=""),"",L6)) -> 0.666 | N6: Governo do Acre alinha políticas públicas ambientais que serão executadas em parceria com governo federal e municípios. O Acre aderiu ao projeto Floresta+ Amazônia, do Ministério de Meio Ambiente (MMA), e já deu início ao processo de adesão para que produtores rurais possam ser remunerados por manterem suas florestas em pé para além do exigido por lei. O Governo do Acre tem estabelecido diversas parcerias com o governo federal para fortalecer políticas ambientais no estado, com foco na preservação da Amazônia e no combate ao desmatamento. Essas parcerias envolvem ações de regularização ambiental, restauração florestal, bioeconomia e enfrentamento aos efeitos das mudanças climáticas. O Fundo Brasil-ONU é uma parceria estratégica entre o Consórcio da Amazônia Legal (CAL), a ONU Brasil e o governo federal, com o objetivo de apoiar a implementação de soluções sustentáveis e inclusivas para os desafios da Amazônia. O Acre foi contemplado pelo Fundo Brasil-ONU para a Amazônia. São mais de R$ 15 milhões que serão investidos no fortalecimento da governança ambiental, na restauração florestal, segurança hídrica e na bioeconomia. Não foi possível encontrar um mapeamento sistemático oportunidades de adesão. | P6: P
A7: 7970 | B7: Financiamento | C7: F2 | D7: Captação de recursos | E7: B | F7: Estado | G7: Acre | H7: 12 | I7: 45912.645 | J7: Versão de Avaliação 2025 | K7: Estágio avançado | L7: 1 | M7: =IF(K7="Sem progresso",0,IF(OR(K7="Não avaliado",K7="Não se aplica",K7=""),"",L7)) -> 1 | N7: O Acre tem se destacado na adesão e implementação de programas e políticas federais relacionadas ao clima, com foco na redução do desmatamento, promoção da sustentabilidade e adaptação às mudanças climáticas. O estado tem recebido investimentos significativos do governo federal e parcerias internacionais para projetos ambientais, incluindo programas como REDD+ e a recuperação de áreas degradadas. O governo do Acre, por meio da Secretaria de Estado de Meio Ambiente (Sema), tem trabalhado para alinhar políticas públicas ambientais com o governo federal e os municípios. O Programa REM e o Projeto Rumo ao Desmatamento Ilegal Zero com o Fundo Amazônia reafirmam a posição de vanguarda do Acre na proteção do meio ambiente. Juntas, essas iniciativas possibilitarão ao governo estadual empregar mais de R$ 138 milhões, no próximo ano, em ações de fortalecimento das políticas de sustentabilidade florestal e combate ao desmatamento ilegal. | P7: P
A8: 7987 | B8: Financiamento | C8: F2 | D8: Captação de recursos | E8: C | F8: Estado | G8: Acre | H8: 12 | I8: 45912.645 | J8: Versão de Avaliação 2025 | K8: Estágio intermediário | L8: 0.666 | M8: =IF(K8="Sem progresso",0,IF(OR(K8="Não avaliado",K8="Não se aplica",K8=""),"",L8)) -> 0.666 | N8: O governo do Acre, em colaboração com o governo federal, realiza o monitoramento da execução físico-financeira das políticas ambientais no estado. O governo do Acre tem parceria com o Ministério do Meio Ambiente (MMA) e municípios para o desenvolvimento de políticas públicas ambientais. Projetos como o "Pagamento por Serviços Ambientais (PSA) Agricultor" e o "Floresta+ Amazônia" são exemplos de iniciativas conjuntas. O estado também busca recursos de outras fontes, como o Fundo Amazônia, para financiar projetos de conservação ambiental. As ações de mobilização de investimentos são monitoradas com regularidade e as informações disponibilizadas e encontradas atendem parcialmente os atributos 2 e 3. Os recursos do Programa REM ACre Fase II podem ser acompanhadas na página eletrônica do programa e são atualizadas e de fácil compreensão. | P8: P
A9: 7562 | B9: Financiamento | C9: F3 | D9: Mobilização de investimento privado | E9: A | F9: Estado | G9: Acre | H9: 12 | I9: 45912.645 | J9: Versão de Avaliação 2025 | K9: Estágio inicial | L9: 0.333 | M9: =IF(K9="Sem progresso",0,IF(OR(K9="Não avaliado",K9="Não se aplica",K9=""),"",L9)) -> 0.333 | N9: Acre capta mais de U$ 300 milhões para investimentos Na Conferência das Nações Unidas sobre as Mudanças Climáticas (COP27), no Egito, o Estado do Acre prospectou mais de U$ 300 milhões que irão garantir investimentos em políticas de sustentabilidade para os próximos 4 anos. Com a U.S. Agency for International Development (Usaid), estão previstos mais de U$ 250 mil para desenvolvimento de projetos voltados para a sustentabilidade e o reflorestamento, para o fortalecimento de cadeias produtivas locais e melhoria da qualidade de vida daqueles que vivem na floresta. parceria foi firmada com a Noruega para captação de U$ 8 milhões destinados à recuperação de áreas degradadas, melhoramento do uso do solo, a diversificação da produção, a melhoria da geração de renda e dos serviços ambientais e ecossistêmicos. Já o fundo canadense se dispôs a investir U$ 30 milhões para ações voltadas para a bioeconomia. A Mercuria Trading S.A., uma empresa privada suíça, se propôs a contribuir com as políticas de comando e controle do desmatamento e incêndios florestais, a fim de viabilizar a captação mais de U$ 2 milhões. O programa REM, financiado pelos governos alemão (Banco KfW) e inglês (Beis), disponibilizará mais de U$ 13 milhões para o Acre. transparência e preparação da população. | P9: P
A10: 7583 | B10: Financiamento | C10: F3 | D10: Mobilização de investimento privado | E10: B | F10: Estado | G10: Acre | H10: 12 | I10: 45912.645 | J10: Versão de Avaliação 2025 | K10: Sem progresso | M10: =IF(K10="Sem progresso",0,IF(OR(K10="Não avaliado",K10="Não se aplica",K10=""),"",L10)) -> 0 | N10: Não foram encontradas as ações de mobilização de investimento privado que sejam monitoradas regularmente e que a informação seja disponibilizada de forma a atender totalmente aos atributos de transparência, acessibilidade e usabilidade Não foram localizadas evidências que demonstrem a existência de tal sistema de monitoramento e transparencia para o investimento privado. | P10: P
A11: 9925 | B11: Financiamento | C11: F1 | D11: Finanças e gastos públicos | E11: A | F11: Estado | G11: Alagoas | H11: 27 | I11: 45951.8 | J11: Versão de Avaliação 2025 | K11: Estágio avançado | L11: 1 | M11: =IF(K11="Sem progresso",0,IF(OR(K11="Não avaliado",K11="Não se aplica",K11=""),"",L11)) -> 1 | N11: O PPA do Estado de Alagoas inclui o enfrentamento das mudanças climáticas como uma das suas diretrizes, alocando recursos em seus orçamentos anuais para ações ou iniciativas direcionadas ao enfrentamento da mudança do clima e seus impactos. Dentre as ações, pode-se citar: 1 - OPERAR, MANTER E AMPLIAR A REDE DE ESTAÇÕES METEOROLÓGICAS, HIDROLÓGICAS E PLUVIOMÉTRICAS DO SISTEMA DE MONITORAMENTO DE DESASTRES NATURAIS NO ESTADO DE ALAGOAS. 2 - CONSTRUIR BARRAGENS E REALIZAR AÇÕES DE PREVENÇÕES DE DESASTRES AMBIENTAIS NAS BACIAS HIDROGRÁFICAS. 3 - CONSCIENTIZAR A POPULAÇÃO E DISSERMINAR INFORMAÇÕES SOBRE A IMPORTÂNCIA DE SE PRESERVAR O MEIO AMBIENTE. 4 - IMPLANTAR E PROMOVER A POLÍTICA DE EDUCAÇÃO AMBIENTAL NO ESTADO, GARANTINDO A CONSERVAÇÃO E A MANUTENÇÃO DA BIODIVERSIDADE, PROMOVENDO A CONSERVAÇÃO DOS SOLOS, A PRODUÇÃO AGRÍCOLA, A BIODIVERSIDADE E A CONVIVÊNCIA SUSTENTAVÉL COM A SEMIARIDEZ EM REGIÕES SUSCETÍVEIS À DESERTIFICAÇÃO, E PROMOVENDO DIRETRIZES GERAIS DE DISCIPLINAMENTO DE USO E OCUPAÇÃO NATURAL E ECONÔNICA DA ZONA COSTEIRA. 5 - ELABORAR O PLANO DE AÇÃO CLIMÁTICA, OBJETIVANDO CRIAR ESTRATÉGIAS VOLTADAS ÀS MUDANÇAS CLIMÁTICAS. 6 - MANTER A SALA DE ALERTA E O SISTEMA DE ALERTA CLIMÁTICO DE ALAGOAS. | P11: P
A12: 9961 | B12: Financiamento | C12: F1 | D12: Finanças e gastos públicos | E12: B | F12: Estado | G12: Alagoas | H12: 27 | I12: 45951.8 | J12: Versão de Avaliação 2025 | K12: Sem progresso | M12: =IF(K12="Sem progresso",0,IF(OR(K12="Não avaliado",K12="Não se aplica",K12=""),"",L12)) -> 0 | N12: Conforme resposta do jurisdicionado ao RI, bem como após analisar o QDD 2024 e 2025, verifica-se que não há uma metodologia para identificar, mensurar e classificar os gastos direcionados a ações climáticas no orçamento. Os códigos ou rubricas são variados, não diferenciando os gastos diretos em ações climáticas de outros tipos de despesa administrativas ou setorial. Desse modo, não é possível o atendimento aos critérios de 1 a 4 da metodologia do Painel ClimaBrasil. | P12: P
A13: 9926 | B13: Financiamento | C13: F1 | D13: Finanças e gastos públicos | E13: C | F13: Estado | G13: Alagoas | H13: 27 | I13: 45951.8 | J13: Versão de Avaliação 2025 | K13: Estágio intermediário | L13: 0.666 | M13: =IF(K13="Sem progresso",0,IF(OR(K13="Não avaliado",K13="Não se aplica",K13=""),"",L13)) -> 0.666 | N13: A Lei nº 9.304/2024 estabelece como objetivos a redução das emissões de GEE e a promoção de ações de adaptação às mudanças climáticas, incluindo: 1. Implementação de ações de prevenção e adaptação às alterações produzidas pelos impactos das mudanças climáticas, visando proteger principalmente os estratos mais vulneráveis da população. 2. Promoção de compras e contratações sustentáveis pelo Poder Público, com base em critérios de sustentabilidade, em particular com vistas ao equilíbrio climático. Neste mesmo sentido, o Estado de Alagoas tem investido na capacitação técnica para viabilizar a inclusão de critérios de sustentabilidade nas compras públicas. Destaca-se a exigência de Declaração de Sustentabilidade nos editais, conforme a lei 14.133/21 Por fim, o Selo Alagoas pelo Clima reconhece publicamente as organizações que realizam e registram seus inventários de emissões de GEE, promovendo a adoção de boas práticas e a descarbonização de seus processos. Em relação aos critérios relacionados à redução de GEE e adaptação às mudanças climáticas nas compras públicas estaduais, há indicativos de ações concretas como a aquisição de Aquisição de Arla 32 para frota a diesel, a fim de reduzir emissões de óxidos de nitrogênio (NOx). | P13: P
A14: 9962 | B14: Financiamento | C14: F1 | D14: Finanças e gastos públicos | E14: D | F14: Estado | G14: Alagoas | H14: 27 | I14: 45951.8 | J14: Versão de Avaliação 2025 | K14: Sem progresso | M14: =IF(K14="Sem progresso",0,IF(OR(K14="Não avaliado",K14="Não se aplica",K14=""),"",L14)) -> 0 | N14: Não há marcador climático no orçamento. Desse modo, este item fica prejudicado. Ademais, as evidências apresentadas pelo ente jurisdicionado, bem como as pesquisas efetuadas pela Equipe de Auditoria em sites oficiais, não foram adequadas e suficientes para comprovar o atendimento aos critérios do item, conforme a Metodologia do Painel ClimaBrasil. | P14: P
A15: 9927 | B15: Financiamento | C15: F2 | D15: Captação de recursos | E15: A | F15: Estado | G15: Alagoas | H15: 27 | I15: 45951.8 | J15: Versão de Avaliação 2025 | K15: Estágio inicial | L15: 0.333 | M15: =IF(K15="Sem progresso",0,IF(OR(K15="Não avaliado",K15="Não se aplica",K15=""),"",L15)) -> 0.333 | N15: AdaptaCidades: Adesão formalizada, com previsão de apoio técnico a municípios, mas sem publicação de plano de ação estadual Plano ABC+ Alagoas: Lançado, porém ainda em fase inicial de execução (sem metas monitoradas publicamente) No entanto, não há registro público de um mapeamento sistemático ou documento estadual que organize de forma integrada todas as oportunidades de financiamento climático, sejam federais, multilaterais (como GCF, BID, BNDES Fundo Clima) ou por meio de políticas setoriais. Quanto a capacidade operacional, algumas ações são descentralizadas em diferentes secretarias/órgãos (Meio Ambiente, Infraestrutura, Agricultura, IMA), levando a atuações isoladas, o que dificulta a integração das informações geradas pelos diferentes atores. | P15: P
A16: 9963 | B16: Financiamento | C16: F2 | D16: Captação de recursos | E16: B | F16: Estado | G16: Alagoas | H16: 27 | I16: 45951.8 | J16: Versão de Avaliação 2025 | K16: Sem progresso | M16: =IF(K16="Sem progresso",0,IF(OR(K16="Não avaliado",K16="Não se aplica",K16=""),"",L16)) -> 0 | N16: Conforme respostas fornecidas pelo jurisdicionado ao RI, na página 30: "Há iniciativas de apresentação de projetos em Brasília e captação de recursos (ex.: ações conjuntas com SERFI para transição energética e projetos estruturantes)". Não foram fornecidos mapeamentos ou informações adicionais sobre os projetos/oportunidades de financiamento atualmente buscados/identificados pelo governo de Alagoas, sendo evidenciado apenas que havia iniciativas a serem apresentadas, mas nada concretizado até a presente avaliação. | P16: P
A17: 9964 | B17: Financiamento | C17: F2 | D17: Captação de recursos | E17: C | F17: Estado | G17: Alagoas | H17: 27 | I17: 45951.8 | J17: Versão de Avaliação 2025 | K17: Sem progresso | M17: =IF(K17="Sem progresso",0,IF(OR(K17="Não avaliado",K17="Não se aplica",K17=""),"",L17)) -> 0 | N17: Não foram identificadas/fornecidas evidências de que há ações para a captação de recursos para execução de ações de política climática monitoradas de modo contínuo e/ou regular (ao menos uma vez). Não foram identificados/fornecidas evidências de que há sistemas, relatórios, websites ou outras ferramentas ou plataformas específicas (mecanismos) que apresentem dados sobre a captação de recursos para execução de ações de política climática de modo contínuo, com dados atualizados e disponíveis para pesquisa e auditoria (transparência ativa). | P17: P
A18: 9928 | B18: Financiamento | C18: F3 | D18: Mobilização de investimento privado | E18: A | F18: Estado | G18: Alagoas | H18: 27 | I18: 45951.8 | J18: Versão de Avaliação 2025 | K18: Estágio avançado | L18: 1 | M18: =IF(K18="Sem progresso",0,IF(OR(K18="Não avaliado",K18="Não se aplica",K18=""),"",L18)) -> 1 | N18: As evidências demonstram a existência de pelo menos dois mecanismos operacionais: 1. O Programa Cresce Alagoas, que oferece incentivos tributários. 2. O Programa Estadual de Pagamento por Serviços Ambientais (PROPSA), com editais lançados e em fase de pagamento. Assim, há evidências de que o ente mobilizou recursos privados em ações que contribuem para o alcance dos objetivos climáticos (nos exercícios de 2024-2025). A EXIGEN 1, biorrefinaria pioneira de biocombustíveis sustentáveis avançados do Brasil, fruto de uma aliança estratégica entre GranBio, Usina Caeté, Usina Santo Antônio e Impacto Bioenergia, é responsável por atrair investimentos da ordem de R$ 1,5 bilhão até 2028. | P18: P
A19: 9929 | B19: Financiamento | C19: F3 | D19: Mobilização de investimento privado | E19: B | F19: Estado | G19: Alagoas | H19: 27 | I19: 45951.8 | J19: Versão de Avaliação 2025 | K19: Sem progresso | M19: =IF(K19="Sem progresso",0,IF(OR(K19="Não avaliado",K19="Não se aplica",K19=""),"",L19)) -> 0 | N19: Não foram fornecidas evidências de atendimento a este critério pelo ente jurisdicionado. Também não ficou evidenciado se há ações para a mobilização de recursos privados para financiamento climático e, em havendo, se são monitoradas de modo contínuo e regular (ao menos uma vez ao ano) pelo Estado. | P19: P
A20: 6665 | B20: Financiamento | C20: F1 | D20: Finanças e gastos públicos | E20: A | F20: Estado | G20: Amapá | H20: 16 | I20: 45938.683 | J20: Versão de Avaliação 2025 | K20: Estágio intermediário | L20: 0.666 | M20: =IF(K20="Sem progresso",0,IF(OR(K20="Não avaliado",K20="Não se aplica",K20=""),"",L20)) -> 0.666 | N20: O PPA 2024-2027 e a LOA 2025 preveem programas e ações alinhados ao ODS 13, como "Governança Ambiental Sustentável" e "Tesouro Verde", com dotações específicas para políticas de clima e serviços ambientais. Contudo, os valores são reduzidos frente ao orçamento total, concentram-se na área ambiental e não há Plano Estadual de Mudanças Climáticas plenamente integrado. | P20: P
A21: 6666 | B21: Financiamento | C21: F1 | D21: Finanças e gastos públicos | E21: B | F21: Estado | G21: Amapá | H21: 16 | I21: 45938.683 | J21: Versão de Avaliação 2025 | K21: Sem progresso | M21: =IF(K21="Sem progresso",0,IF(OR(K21="Não avaliado",K21="Não se aplica",K21=""),"",L21)) -> 0 | N21: O Estado do Amapá não possui mecanismos formais para identificar e rastrear despesas orçamentárias, diretas ou indiretas, relacionadas a ações de mitigação/adaptação ou prejudiciais aos objetivos climáticos. As dotações existentes no PPA e LOA não estão classificadas como "gasto climático" nem integradas a sistema de monitoramento específico e tampouco foi demonstrado pela SEMA/AP em resposta oficial. | P21: P
A22: 6668 | B22: Financiamento | C22: F1 | D22: Finanças e gastos públicos | E22: C | F22: Estado | G22: Amapá | H22: 16 | I22: 45938.683 | J22: Versão de Avaliação 2025 | K22: Estágio inicial | L22: 0.333 | M22: =IF(K22="Sem progresso",0,IF(OR(K22="Não avaliado",K22="Não se aplica",K22=""),"",L22)) -> 0.333 | N22: Embora o Estado do Amapá possua o Manual Prático de Contratações Sustentáveis e base legal que prevê a adoção de critérios ambientais e climáticos, não há evidências consolidadas de aplicação sistemática e monitorada desses critérios nos processos licitatórios. As iniciativas identificadas concentram-se em orientações gerais e exemplos, mas sem comprovação de que sejam incorporadas de forma rotineira nos editais, contratos e licitações. | P22: P
A23: 6687 | B23: Financiamento | C23: F1 | D23: Finanças e gastos públicos | E23: D | F23: Estado | G23: Amapá | H23: 16 | I23: 45938.683 | J23: Versão de Avaliação 2025 | K23: Estágio inicial | L23: 0.333 | M23: =IF(K23="Sem progresso",0,IF(OR(K23="Não avaliado",K23="Não se aplica",K23=""),"",L23)) -> 0.333 | N23: O Estado do Amapá disponibiliza receitas e despesas em formato aberto (CSV), com dados detalhados e atualizados, atendendo à transparência ativa. Contudo, não há categorização específica para gastos climáticos ou contratações emergenciais, nem linguagem simplificada ou metadados que facilitem a compreensão pelo cidadão, | P23: P
A24: 6689 | B24: Financiamento | C24: F2 | D24: Captação de recursos | E24: A | F24: Estado | G24: Amapá | H24: 16 | I24: 45938.683 | J24: Versão de Avaliação 2025 | K24: Estágio intermediário | L24: 0.666 | M24: =IF(K24="Sem progresso",0,IF(OR(K24="Não avaliado",K24="Não se aplica",K24=""),"",L24)) -> 0.666 | N24: O Estado do Amapá demonstra capacidade de adesão a instrumentos e programas vinculados a planos climáticos e setoriais nacionais por meio da participação em iniciativas como o Programa de Consolidação do Pacto Nacional pela Gestão das Águas - Progestão e o Plano de Prevenção e Controle do Desmatamento na Amazônia Legal - PPCDAM. Devido à adesão comprovada e à implementação de medidas efetivas, mas com possibilidade de evolução para avançado mediante maior integração intersetorial e monitoramento ampliado. | P24: P
A25: 6692 | B25: Financiamento | C25: F2 | D25: Captação de recursos | E25: B | F25: Estado | G25: Amapá | H25: 16 | I25: 45938.683 | J25: Versão de Avaliação 2025 | K25: Estágio intermediário | L25: 0.666 | M25: =IF(K25="Sem progresso",0,IF(OR(K25="Não avaliado",K25="Não se aplica",K25=""),"",L25)) -> 0.666 | N25: Há evidências de execução local com participação da SEMA e parceiros técnicos, demonstrando capacidade de captar e aplicar recursos externos. Contudo, a escala ainda é limitada e concentrada em poucos programas, sem portfólio diversificado e sistemático que envolva fundos nacionais como Fundo Clima ou operações com BNDES e GCF. | P25: P
A26: 6695 | B26: Financiamento | C26: F2 | D26: Captação de recursos | E26: C | F26: Estado | G26: Amapá | H26: 16 | I26: 45938.683 | J26: Versão de Avaliação 2025 | K26: Sem progresso | M26: =IF(K26="Sem progresso",0,IF(OR(K26="Não avaliado",K26="Não se aplica",K26=""),"",L26)) -> 0 | N26: Não foram identificadas evidências de mecanismos específicos e operacionais no Estado do Amapá para monitorar e divulgar de forma sistemática informações sobre o uso de recursos captados em financiamentos climáticos, nem sobre os resultados obtidos com sua aplicação. | P26: P
A27: 6696 | B27: Financiamento | C27: F3 | D27: Mobilização de investimento privado | E27: A | F27: Estado | G27: Amapá | H27: 16 | I27: 45938.683 | J27: Versão de Avaliação 2025 | K27: Estágio inicial | L27: 0.333 | M27: =IF(K27="Sem progresso",0,IF(OR(K27="Não avaliado",K27="Não se aplica",K27=""),"",L27)) -> 0.333 | N27: O Estado do Amapá aprovou a Lei nº 3.152/2024, que concede isenção de IPVA para veículos elétricos e híbridos até 2026, configurando incentivo fiscal climático. Além disso, o Estado dispõe do Programa Tesouro Verde, criado para promover a valoração de ativos ambientais e atrair recursos privados destinados à conservação e ao desenvolvimento sustentável. Entretanto, o Tesouro Verde encontra-se paralisado desde o início de 2023, sem execução orçamentária, operacionalização de projetos ou evidências de resultados concretos. Dessa forma, embora haja mecanismos instituídos, a ausência de implementação prática | P27: P
A28: 6698 | B28: Financiamento | C28: F3 | D28: Mobilização de investimento privado | E28: B | F28: Estado | G28: Amapá | H28: 16 | I28: 45938.683 | J28: Versão de Avaliação 2025 | K28: Sem progresso | M28: =IF(K28="Sem progresso",0,IF(OR(K28="Não avaliado",K28="Não se aplica",K28=""),"",L28)) -> 0 | N28: Não foram identificadas evidências de que o Estado do Amapá possua mecanismos para monitorar a mobilização de financiamento climático privado ou para divulgar de forma sistemática os resultados obtidos com esses recursos. Não há registros públicos de relatórios, indicadores ou sistemas de acompanhamento específicos sobre investimentos privados em ações de mitigação ou adaptação. | P28: P
A29: 1887 | B29: Financiamento | C29: F1 | D29: Finanças e gastos públicos | E29: A | F29: Estado | G29: Amazonas | H29: 13 | I29: 45915.675 | J29: Versão de Avaliação 2025 | K29: Sem progresso | M29: =IF(K29="Sem progresso",0,IF(OR(K29="Não avaliado",K29="Não se aplica",K29=""),"",L29)) -> 0 | N29: Apesar de constar no Orçamento de 2025, a ação "Serviços Ambientais, Adaptação e Mitigação às Mudanças do Clima", o valor orçamentário alocado é de apenas R$ 1.054,00" | P29: P
A30: 1893 | B30: Financiamento | C30: F1 | D30: Finanças e gastos públicos | E30: B | F30: Estado | G30: Amazonas | H30: 13 | I30: 45915.675 | J30: Versão de Avaliação 2025 | K30: Estágio inicial | L30: 0.333 | M30: =IF(K30="Sem progresso",0,IF(OR(K30="Não avaliado",K30="Não se aplica",K30=""),"",L30)) -> 0.333 | N30: A estrutura apresentada no PPA possibilita apenas, identificar, mensurar e classificar os gastos direcionados a ações climaticas no orçamento. Não é possível diferenciar recursos diretors ou outros tipos de despesas administrativas setoriais, bem como recursos indiretos que contribuam para os objetivos climáticos. | P30: P
A31: 9366 | B31: Financiamento | C31: F1 | D31: Finanças e gastos públicos | E31: C | F31: Estado | G31: Amazonas | H31: 13 | I31: 45915.675 | J31: Versão de Avaliação 2025 | K31: Estágio inicial | L31: 0.333 | M31: =IF(K31="Sem progresso",0,IF(OR(K31="Não avaliado",K31="Não se aplica",K31=""),"",L31)) -> 0.333 | N31: O Estado adota em seus processos licitatórios, critérios de sustentabilidade. | P31: P
A32: 9355 | B32: Financiamento | C32: F1 | D32: Finanças e gastos públicos | E32: D | F32: Estado | G32: Amazonas | H32: 13 | I32: 45915.675 | J32: Versão de Avaliação 2025 | K32: Sem progresso | M32: =IF(K32="Sem progresso",0,IF(OR(K32="Não avaliado",K32="Não se aplica",K32=""),"",L32)) -> 0 | N32: Não existem sistemas, relatórios ou websites que possibilitem a consulta a dados sobre o orçamento climático. | P32: P
A33: 9357 | B33: Financiamento | C33: F2 | D33: Captação de recursos | E33: A | F33: Estado | G33: Amazonas | H33: 13 | I33: 45915.675 | J33: Versão de Avaliação 2025 | K33: Estágio intermediário | L33: 0.666 | M33: =IF(K33="Sem progresso",0,IF(OR(K33="Não avaliado",K33="Não se aplica",K33=""),"",L33)) -> 0.666 | N33: O Estado desenvolve ações relevantes no combate ao desmatamento, por meio do PPCDQ-AM | P33: P
A34: 9358 | B34: Financiamento | C34: F2 | D34: Captação de recursos | E34: B | F34: Estado | G34: Amazonas | H34: 13 | I34: 45915.675 | J34: Versão de Avaliação 2025 | K34: Estágio intermediário | L34: 0.666 | M34: =IF(K34="Sem progresso",0,IF(OR(K34="Não avaliado",K34="Não se aplica",K34=""),"",L34)) -> 0.666 | N34: O Estado tem mapeadas fontes de recursos e utiliza vários instrumentos, por meio de projetos elaborados por seus técnicos, para acessá-los. | P34: P
A35: 9451 | B35: Financiamento | C35: F2 | D35: Captação de recursos | E35: C | F35: Estado | G35: Amazonas | H35: 13 | I35: 45915.675 | J35: Versão de Avaliação 2025 | K35: Estágio inicial | L35: 0.333 | M35: =IF(K35="Sem progresso",0,IF(OR(K35="Não avaliado",K35="Não se aplica",K35=""),"",L35)) -> 0.333 | N35: Atende ao atributo 1 e parcialmente aos itens 1 e 2. | P35: P
A36: 9381 | B36: Financiamento | C36: F3 | D36: Mobilização de investimento privado | E36: A | F36: Estado | G36: Amazonas | H36: 13 | I36: 45915.675 | J36: Versão de Avaliação 2025 | K36: Sem progresso | M36: =IF(K36="Sem progresso",0,IF(OR(K36="Não avaliado",K36="Não se aplica",K36=""),"",L36)) -> 0 | N36: Não há ações nesse sentido. | P36: P
A37: 9382 | B37: Financiamento | C37: F3 | D37: Mobilização de investimento privado | E37: B | F37: Estado | G37: Amazonas | H37: 13 | I37: 45915.675 | J37: Versão de Avaliação 2025 | K37: Sem progresso | M37: =IF(K37="Sem progresso",0,IF(OR(K37="Não avaliado",K37="Não se aplica",K37=""),"",L37)) -> 0 | N37: Não há ações nesse sentido. | P37: P
A38: 1903 | B38: Financiamento | C38: F1 | D38: Finanças e gastos públicos | E38: A | F38: Estado | G38: Bahia | H38: 29 | I38: 45901.867 | J38: Versão de Avaliação 2025 | K38: Estágio intermediário | L38: 0.666 | M38: =IF(K38="Sem progresso",0,IF(OR(K38="Não avaliado",K38="Não se aplica",K38=""),"",L38)) -> 0.666 | N38: "O PPA vigente (2024 - 2027) prevê a execução do Programa Meio Ambiente e Mudança do Clima, que, dentre outros, objetiva a implementação de ações de adaptação e mitigação das mudanças climáticas. Dentre as iniciativas previstas estão: implementar a Política Estadual de Mudança do Clima
A39: 1890 | B39: Financiamento | C39: F1 | D39: Finanças e gastos públicos | E39: B | F39: Estado | G39: Bahia | H39: 29 | I39: 45901.867 | J39: Versão de Avaliação 2025 | K39: Estágio inicial | L39: 0.333 | M39: =IF(K39="Sem progresso",0,IF(OR(K39="Não avaliado",K39="Não se aplica",K39=""),"",L39)) -> 0.333 | N39: "Na LOA 2025, há ações de mitigação dos efeitos das mudanças climáticas: Implementar o plano Agricultura de Baixo Carbono ABC+Bahia (SDR)
A40: 1892 | B40: Financiamento | C40: F1 | D40: Finanças e gastos públicos | E40: C | F40: Estado | G40: Bahia | H40: 29 | I40: 45901.867 | J40: Versão de Avaliação 2025 | K40: Estágio inicial | L40: 0.333 | M40: =IF(K40="Sem progresso",0,IF(OR(K40="Não avaliado",K40="Não se aplica",K40=""),"",L40)) -> 0.333 | N40: A Auditoria identificou normativos que estabelecem critérios de sustentabilidade nas contratações públicas estaduais, não havendo, especificamente, critérios relacionados à redução de GEE e adaptação à mudança do clima. O Estado sancionou sua nova Lei de Licitações e Contratos (Lei 14.634/2023), alinhando-se a Lei Federal 14.133/2021, estabelecendo o desenvolvimento sustentável como um dos seus princípios. Identificou-se o Decreto Estadual nº 14.692/2013, que instituiu o Programa Est. de Compras Públicas sustentáveis e o Decreto nº 22.598/2024, que trata da elaboração dos ETP's para aquisição de bens e contratação de serviços pelos órgãos e entidades da Adm. Pública direta, autárquica e fundacional do Executivo baiano, determinando, em seu Art. 6º, que dentre os elementos obrigatórios no ETP deverá estar presente "descrição de possíveis impactos ambientais e respectivas medidas mitigadoras, incluídos requisitos de baixo consumo de energia e de outros recursos, bem como logística reversa para desfazimento e reciclagem de bens e refugos, quando aplicável". Verificou-se, ainda, a Instrução Normativa SAEB nº 015/2014, que orienta sobre sustentabilidade ambiental na aquisição de bens e contratações de serviços de Tecnologia da Informação e Comunicação e a Instrução Normativa SAEB 003/2024, que orienta os órgãos e entidades do Executivo Estadual quanto à elaboração dos ETPs, prevendo, em anexo único, , modelo padronizado que expressamente exige a avaliação de impactos ambientais. | P40: P
A41: 1894 | B41: Financiamento | C41: F1 | D41: Finanças e gastos públicos | E41: D | F41: Estado | G41: Bahia | H41: 29 | I41: 45901.867 | J41: Versão de Avaliação 2025 | K41: Estágio inicial | L41: 0.333 | M41: =IF(K41="Sem progresso",0,IF(OR(K41="Não avaliado",K41="Não se aplica",K41=""),"",L41)) -> 0.333 | N41: Não existe, nos sites dos órgãos ambientais estaduais, uma transparência específica acerca das ações e gastos dentro da Política Estadual de Mudança do Clima (ou outras políticas estaduais ambientais). O que existe, no âmbito estadual, é o Portal da Transparência do Estado da Bahia (www.transparencia.ba.gov.br ), que oferece à sociedade uma consulta detalhada das despesas executadas pelo Poder Público, por ação orçamentária, inclusive aquelas vinculadas diretamente à política climática, a exemplo da Ação 3070 - Elaboração de Estudo de Mudança do Clima. Tal ferramenta digital oficial possibilita a pesquisa dos gastos ocorridos em programas estaduais, o que inclui as políticas públicas ambientais. | P41: P
A42: 1921 | B42: Financiamento | C42: F2 | D42: Captação de recursos | E42: A | F42: Estado | G42: Bahia | H42: 29 | I42: 45901.867 | J42: Versão de Avaliação 2025 | K42: Estágio inicial | L42: 0.333 | M42: =IF(K42="Sem progresso",0,IF(OR(K42="Não avaliado",K42="Não se aplica",K42=""),"",L42)) -> 0.333 | N42: "A Auditoria identificou programas e iniciativas da União destinados a mitigação e adaptação às mudanças climáticas. Dentre os principais, destacam-se a Política Nacional sobre Mudança do Clima, o Plano Clima, o Fundo Clima, o Plano de Ação Brasileiro de Combate à Desertificação e Mitigação dos Efeitos da Seca
A43: 6724 | B43: Financiamento | C43: F2 | D43: Captação de recursos | E43: B | F43: Estado | G43: Bahia | H43: 29 | I43: 45901.867 | J43: Versão de Avaliação 2025 | K43: Sem progresso | M43: =IF(K43="Sem progresso",0,IF(OR(K43="Não avaliado",K43="Não se aplica",K43=""),"",L43)) -> 0 | N43: O Estado da Bahia não dispõe de mapeamento de oportunidades de financiamento para as ações climáticas, com identificação de linhas para projetos prioritários, com um planejamento estratégico para acesso a fontes externas. Segundo informado pela SEMA: "As articulações para obtenção de financiamentos destinados às ações climáticas são realizadas conforme a disponibilidade e as oportunidades apresentadas pelos editais e chamadas públicas. Como exemplo, destaca-se o Projeto Sertão Vivo, sob a administração da Companhia de Desenvolvimento e Ação Regional - CAR, lançado em julho de 2025, fruto de cooperação entre o Governo da Bahia, o Banco Nacional de Desenvolvimento Econômico e Social (BNDES), o Fundo Internacional de Desenvolvimento Agrícola (FIDA) e o Fundo Verde Clima. | P43: P
A44: 6803 | B44: Financiamento | C44: F2 | D44: Captação de recursos | E44: C | F44: Estado | G44: Bahia | H44: 29 | I44: 45901.867 | J44: Versão de Avaliação 2025 | K44: Sem progresso | M44: =IF(K44="Sem progresso",0,IF(OR(K44="Não avaliado",K44="Não se aplica",K44=""),"",L44)) -> 0 | N44: A SEMA, conforme transcrito a seguir, informou acerca da inexistência de mecanismos de monitoramento de captação de recursos: Atualmente, a Secretaria do Meio Ambiente não dispõe de mecanismo formal e sistematizado de monitoramento contínuo ou periódico específico para as ações de captação de recursos voltadas à política climática. No entanto, a Pasta reconhece a relevância desse instrumento para o fortalecimento da gestão ambiental e vem envidando esforços para estruturar procedimentos internos que possibilitem maior rastreabilidade e avaliação das iniciativas desenvolvidas. Diante disso, como parte do processo de aprimoramento da gestão, estão sendo avaliadas alternativas viáveis para organizar e reunir, de forma mais sistemática, as informações sobre projetos, parcerias e cooperações técnicas, de modo a facilitar o acompanhamento dessas iniciativas e subsidiar, de maneira mais eficiente, a tomada de decisões relacionadas às ações climáticas no Estado". | P44: P
A45: 6641 | B45: Financiamento | C45: F3 | D45: Mobilização de investimento privado | E45: A | F45: Estado | G45: Bahia | H45: 29 | I45: 45901.867 | J45: Versão de Avaliação 2025 | K45: Estágio intermediário | L45: 0.666 | M45: =IF(K45="Sem progresso",0,IF(OR(K45="Não avaliado",K45="Não se aplica",K45=""),"",L45)) -> 0.666 | N45: Não foi apresentado mapeamento de possíveis oportunidades para incentivar empresas/cidadãos a investirem em ações para mitigação/adaptação das mudanças climáticas. Apesar disto, verificou-se que normativos foram publicados objetivando incentivar o uso de recursos privados em ações para produção/uso de energias renováveis. A Política Estadual de Incentivo à Geração e Aproveitamento de Energia Solar (Lei 13.914/2018) promove a racionalização do consumo energético e o uso de energia solar fotovoltaica, e tem, dentre seus objetivos, conceder incentivos fiscais/tributários às empresas que fabricam equipamentos geradores de energia alternativa. O Plano Estadual para a Economia do Hidrogênio Verde (Decreto 21.200/2022) busca fortalecer a cadeia produtiva do hidrogênio verde e fomentar sua aplicação em setores industriais, de mobilidade e transporte. A Lei 14.638/2023 isentou de IPVA automóveis elétricos. A Lei Estadual 14.889/2025 instituiu o Programa Estadual de Transição Energética, que tem, entre seus objetivos, a diversificação das fontes de produção e abastecimento de energia. Ademais, verificou-se, em auditoria realizada em 2023 por este TCE (gestão florestal de Unidades de Conservação), a concessão, pelo INEMA, de diversas licenças ambientais autorizando empresas privadas a instalarem na Bahia Usinas Produtoras de energia eólica, fonte energética renovável (a Bahia é o segundo maior produtor estadual desta fonte). | P45: P
A46: 6642 | B46: Financiamento | C46: F3 | D46: Mobilização de investimento privado | E46: B | F46: Estado | G46: Bahia | H46: 29 | I46: 45901.867 | J46: Versão de Avaliação 2025 | K46: Sem progresso | M46: =IF(K46="Sem progresso",0,IF(OR(K46="Não avaliado",K46="Não se aplica",K46=""),"",L46)) -> 0 | N46: "Através do item 14 da Solicitação MSOL.003.2025 foi requerida a seguinte informação: ""A mobilização destes recursos privados para financiamento climático (caso existam) são monitoradas de modo contínuo e regular (ao menos uma vez ao ano) pelo estado?"". Não foi apresentada nenhuma resposta acerca desta questão. Ademais, a Auditoria não verificou, nos sites dos órgãos ambientais ou outras fontes, qualquer ferramenta publicizando informações desta natureza (se as ações para a mobilização de recursos privados para financiamento climático são monitoradas de modo contínuo e regular
A47: 4323 | B47: Financiamento | C47: F1 | D47: Finanças e gastos públicos | E47: A | F47: Município | G47: Belo Horizonte | H47: 3106200 | I47: 45896.513 | J47: Versão de Avaliação 2025 | K47: Estágio avançado | L47: 1 | M47: =IF(K47="Sem progresso",0,IF(OR(K47="Não avaliado",K47="Não se aplica",K47=""),"",L47)) -> 1 | N47: "A Prefeitura de Belo Horizonte informou que a LDO de 2025 estabelece como prioridades, da área de resultado Sustentabilidade Ambiental, o ""enfrentamento às mudanças climáticas por meio de monitoramento das emissões e execução de ações práticas para redução e sequestro de carbono"" (Art. 2°, VIII, n). Informou, também, que o PPAG (2025) do Município apresenta um conjunto de programas e ações, dentro da área de resultado Sustentabilidade Ambiental, que visam atender essas diretrizes e estão devidamente alinhados com as ações previstas no Plano de Ação Climática e no Plano de Redução de Emissões de GEE - PREGEE. Conforme o Manual de Aplicação, deve ser verificado: 1)Se o PPA do estado ou município inclui o enfrentamento das mudanças climáticas como uma das suas diretrizes
A48: 4361 | B48: Financiamento | C48: F1 | D48: Finanças e gastos públicos | E48: B | F48: Município | G48: Belo Horizonte | H48: 3106200 | I48: 45896.513 | J48: Versão de Avaliação 2025 | K48: Estágio inicial | L48: 0.333 | M48: =IF(K48="Sem progresso",0,IF(OR(K48="Não avaliado",K48="Não se aplica",K48=""),"",L48)) -> 0.333 | N48: "A Prefeitura de Belo Horizonte (PBH) informou que está em desenvolvimento o Orçamento Temático-OT Mudanças Climáticas, para identificar todas as ações de mitigação e adaptação. Informou, também, que está disponível o Painel do OT ODS, para identificar as ações orçamentárias relacionadas ao ODS 13 (Ação Contra a Mudança Global do Clima). Ademais, informou que um dos projetos transformadores da PBH é o ""Resiliência e Mudanças Climáticas"", que será incorporado como Programa dentro do PPAG, com ações e valores monitorados. Conforme o Manual de Aplicação, deve ser verificado: 1)Se adota metodologia para identificar, mensurar e classificar os gastos direcionados a ações climáticas em seu orçamento
A49: 4342 | B49: Financiamento | C49: F1 | D49: Finanças e gastos públicos | E49: C | F49: Município | G49: Belo Horizonte | H49: 3106200 | I49: 45896.513 | J49: Versão de Avaliação 2025 | K49: Estágio inicial | L49: 0.333 | M49: =IF(K49="Sem progresso",0,IF(OR(K49="Não avaliado",K49="Não se aplica",K49=""),"",L49)) -> 0.333 | N49: A Prefeitura informou que o Plano de Ação Climática estabelece, como meta, realizar 10% das compras de alimentos para escolas públicas, via Caixa Escolar, de produtores urbanos até 2030. Informou, também, que o Plano de Redução de Emissões de GEE estabelece na Linha de Ação "Eficiência Energética" a elaboração de uma diretriz central de compras sustentáveis, contudo, essa ação ainda não foi iniciada, estando seu início previsto no PPAG 26/29. Finalmente, informou que a ação de "Promover a permanente substituição de frota de transporte coletivo por veículos menos emissores" está prevista no PREGEE, no PlanMob-BH e no Plano Diretor, porém para ocorrer até 2030. Considerando as evidências anexadas (A Lei 11181/2019 e "O Plano de Mobilidade de Belo Horizonte - PlanMob-BH"), e considerando a própria informação da Prefeitura de que algumas ações estão previstas para serem realizadas até 2030, portanto, ainda são incipientes. Portanto, avalia-se que existem mecanismos que promovem em parte a adoção de critérios e práticas de mitigação/adaptação nas compras e contratações públicas, porém as ações relacionadas a esses mecanismos são incipientes. Desse modo, considerando que de acordo com o Manual de Aplicação, deve ser verificado se o Município possui mecanismos para a inclusão de critérios e práticas de redução da emissão de GEE e/ou de adaptação à mudança do clima, nas compras e contratações públicas, a classificação é "Estágio Inicial", quanto a esse item. | P49: P
A50: 4362 | B50: Financiamento | C50: F1 | D50: Finanças e gastos públicos | E50: D | F50: Município | G50: Belo Horizonte | H50: 3106200 | I50: 45896.513 | J50: Versão de Avaliação 2025 | K50: Estágio intermediário | L50: 0.666 | M50: =IF(K50="Sem progresso",0,IF(OR(K50="Não avaliado",K50="Não se aplica",K50=""),"",L50)) -> 0.666 | N50: Belo Horizonte apresenta avanços expressivos na transparência fiscal aplicada ao tema climático. Estão disponíveis ao público o Portal da Transparência, o Portal de Dados Abertos e o Painel do Orçamento Temático ODS, que permitem acompanhar a execução orçamentária em tempo real e em formatos acessíveis. Destaca-se a possibilidade de filtrar os gastos pelo ODS 13 - Ação contra a Mudança Global do Clima, o que possibilita identificar programas e iniciativas ligadas à agenda ambiental. Complementarmente, o Relatório de Execução Anual de Ações Governamentais traz, no capítulo "Sustentabilidade Ambiental", informações sobre projetos e resultados implementados. Esses instrumentos atendem de forma relevante aos critérios de transparência ativa, linguagem simples e dados abertos, pois oferecem painéis visuais e dados em formatos reutilizáveis. Contudo, ainda há possibilidades de aprimoramento: as informações permanecem agregadas, exigindo conhecimento técnico para identificar gastos climáticos específicos, o que limita a plena compreensão pela sociedade. Ademais, não foram encontradas evidências de divulgação de contratações emergenciais em contextos de desastres, aspecto essencial para fortalecer a transparência. Assim, o município demonstra alinhamento aos Objetivos de Desenvolvimento Sustentável e boas práticas de transparência, mas a consolidação de um sistema efetivo requer maior detalhamento das despesas climáticas e a inclusão de dados sobre contratações emergenciais. | P50: P
A51: 4322 | B51: Financiamento | C51: F2 | D51: Captação de recursos | E51: A | F51: Município | G51: Belo Horizonte | H51: 3106200 | I51: 45896.513 | J51: Versão de Avaliação 2025 | K51: Estágio avançado | L51: 1 | M51: =IF(K51="Sem progresso",0,IF(OR(K51="Não avaliado",K51="Não se aplica",K51=""),"",L51)) -> 1 | N51: "A Prefeitura de Belo horizonte informou que o Município apresenta plena capacidade para aderir a programas climáticos nacionais e internacionais, além de possuir uma diretoria (DCFI, art. 49 Decreto 16.682/2017) com equipe técnica capacitada e dedicada a essa finalidade. A Prefeitura informou, também, que os cálculos dos limites previstos no art. 7º da RSF nº 43/2001 resultaram em percentuais inferiores a 80%, e possui nota A+ na CAPAG, demonstrando solidez fiscal e capacidade de pagamento, com diversos projetos de captação de recursos, como a parceria com o ICLEI, o MCMV e o Pró-Moradia. Constatou-se, a partir das evidências anexadas, a observância dos critérios definidos no Manual de Aplicação, a saber: existe um mapeamento das oportunidades de obtenção de recursos a partir da adesão do ente federativo aos instrumentos da PNMC
A52: 4321 | B52: Financiamento | C52: F2 | D52: Captação de recursos | E52: B | F52: Município | G52: Belo Horizonte | H52: 3106200 | I52: 45896.513 | J52: Versão de Avaliação 2025 | K52: Estágio avançado | L52: 1 | M52: =IF(K52="Sem progresso",0,IF(OR(K52="Não avaliado",K52="Não se aplica",K52=""),"",L52)) -> 1 | N52: A Prefeitura de Belo horizonte informou que o Município dispõe de instrumentos e mecanismos que permitem o acesso a diversas fontes de financiamento, como fundos públicos nacionais, recursos de bancos de desenvolvimento, agências de cooperação internacional, como demonstra os contratos anexos. A Prefeitura informou, também, que a capacidade técnica e jurídica da administração municipal (uma Diretoria dedicada, a DCFI) permite a elaboração de propostas, a gestão de convênios, financiamentos, bem como o atendimento a requisitos técnicos, operacionais e de prestação de contas. Conforme Manual de Aplicação, deve-se avaliar em que medida o ente federativo possui mecanismos e capacidades para identificar e acessar fontes de recursos financeiros, para a execução de projetos específicos, no âmbito do enfrentamento da mudança do clima. Nesse sentido, verificou-se que existem mecanismos que atendem a todos esse critérios e, portanto, a classificação é "Estágio Avançado", quanto a esse item. | P52: P
A53: 4341 | B53: Financiamento | C53: F2 | D53: Captação de recursos | E53: C | F53: Município | G53: Belo Horizonte | H53: 3106200 | I53: 45896.513 | J53: Versão de Avaliação 2025 | K53: Estágio intermediário | L53: 0.666 | M53: =IF(K53="Sem progresso",0,IF(OR(K53="Não avaliado",K53="Não se aplica",K53=""),"",L53)) -> 0.666 | N53: A Prefeitura de Belo horizonte informou que o Município possui mecanismos de monitoramento e controle da utilização dos recursos externos, centrados em órgãos internos (planejamento, controle e auditoria), e sistemas informatizados de acompanhamento de projetos, que garantem a rastreabilidade e a efetividade na aplicação dos recursos captados, assegurando a boa governança dos projetos climáticos implementados com recursos externos, e transparência no monitoramento. Conforme Manual de Aplicação, cabe avaliar se se a execução físico-financeira e os resultados das ações e dos projetos são monitorados regularmente (periodicidade anual, pelo menos), e se há disponibilização das informações relacionadas com o progresso e os resultados dessas ações e projetos. Cabe avaliar, também, se as informações divulgadas estão disponíveis (fácil acesso) para consulta e auditoria, bem como se estão estruturadas de modo que qualquer cidadão, órgão de controle ou parte interessada pode compreender o mecanismo, bem como acompanhar seus resultados (dados abertos/desagregados, linguagem simples). Verificou-se que as ações de mobilização de investimento privado climático são monitoradas, e a informação é disponibilizada, atendendo parcialmente aos critérios referidos. Entretanto, não há monitoramento e mecanismos de transparência específicos sobre os financiamentos para a área climática. Desse modo, a classificação é "Estágio Intermediário". | P53: P
A54: 4101 | B54: Financiamento | C54: F3 | D54: Mobilização de investimento privado | E54: A | F54: Município | G54: Belo Horizonte | H54: 3106200 | I54: 45896.513 | J54: Versão de Avaliação 2025 | K54: Estágio intermediário | L54: 0.666 | M54: =IF(K54="Sem progresso",0,IF(OR(K54="Não avaliado",K54="Não se aplica",K54=""),"",L54)) -> 0.666 | N54: "A Prefeitura informou que Belo Horizonte tem um programa de certificação em sustentabilidade de empreendimentos, o Selo BH Sustentável, que a partir de 2021 foi revisado de forma a incorporar ações de sustentabilidade que considerem ações de adaptação em cinco dimensões: permeabilidade e vegetação
A55: 4121 | B55: Financiamento | C55: F3 | D55: Mobilização de investimento privado | E55: B | F55: Município | G55: Belo Horizonte | H55: 3106200 | I55: 45896.513 | J55: Versão de Avaliação 2025 | K55: Sem progresso | M55: =IF(K55="Sem progresso",0,IF(OR(K55="Não avaliado",K55="Não se aplica",K55=""),"",L55)) -> 0 | N55: A Prefeitura de Belo Horizonte informou que o Certificado de Crédito Verde ainda não foi utilizado, por este motivo não existe monitoramento das renúncias fiscais por este meio. Além disso, a Prefeitura informou que os investimentos financeiros para implementar as medidas de sustentabilidade se dão à cargo do empreendedor. Desse modo, não se verifica o monitoramento contínuo e regular relativo à mobilização de recursos privados para financiamento de ações na área climática, conforme previsto no escopo de avaliação relativo ao financiamento do Manual de Aplicação. Por esse motivo, classifica-se Belo Horizonte, quanto a esse item, como "Sem Progresso". | P55: P
A56: 8522 | B56: Financiamento | C56: F1 | D56: Finanças e gastos públicos | E56: A | F56: Município | G56: Belém | H56: 1501402 | I56: 45912.512 | J56: Versão de Avaliação 2025 | K56: Estágio inicial | L56: 0.333 | M56: =IF(K56="Sem progresso",0,IF(OR(K56="Não avaliado",K56="Não se aplica",K56=""),"",L56)) -> 0.333 | N56: O PPA 2022-2025 previu, nos subprogramas "Belém Bem Cuidada", "Belém, Nossa Moradia" e "Belém, Integrada e Acessível", algumas ações indiretamente relacionadas às mudanças do clima. As LOAs de 2024 e de 2025 destinaram recursos próprios para a execução de algumas atividades, projetos e operações especiais, indiretamente relacionadas às mudanças do clima, podendo contribuir para o cumprimento parcial da totalidade das metas previstas no Plano de Ação Climática de Belém (PLAC). | P56: P
A57: 8523 | B57: Financiamento | C57: F1 | D57: Finanças e gastos públicos | E57: B | F57: Município | G57: Belém | H57: 1501402 | I57: 45912.512 | J57: Versão de Avaliação 2025 | K57: Estágio inicial | L57: 0.333 | M57: =IF(K57="Sem progresso",0,IF(OR(K57="Não avaliado",K57="Não se aplica",K57=""),"",L57)) -> 0.333 | N57: Não são utilizadas rubricas específicas para o gastos com ações que contribuam, positivamente ou negativamente, para os objetivos climáticos. Porém, além das despesas fixadas nas LOAs, é possível rastrear os gastos/investimentos que contribuem indiretamente, por meio do filtro da natureza de despesas, não tendo como principal objetivo a mitigação e/ou adaptação climática, sendo disponibilizadas na seguinte página do site institucional: https://portaltransparencia.belem.pa.gov.br/despesas/despesas-detalhadas/. | P57: P
A58: 8524 | B58: Financiamento | C58: F1 | D58: Finanças e gastos públicos | E58: C | F58: Município | G58: Belém | H58: 1501402 | I58: 45912.512 | J58: Versão de Avaliação 2025 | K58: Sem progresso | M58: =IF(K58="Sem progresso",0,IF(OR(K58="Não avaliado",K58="Não se aplica",K58=""),"",L58)) -> 0 | N58: Após consulta no site da Câmara Municipal e da Prefeitura Municipal de Belém, não restou comprovada a existência de mecanismos que promovam a adoção de critérios e práticas de sustentabilidade, redução da emissão de Gases de Efeito Estufa - GEE, nem adaptação às mudanças do clima nas compras e contratações públicas do ente. | P58: P
A59: 8525 | B59: Financiamento | C59: F1 | D59: Finanças e gastos públicos | E59: D | F59: Município | G59: Belém | H59: 1501402 | I59: 45912.512 | J59: Versão de Avaliação 2025 | K59: Estágio inicial | L59: 0.333 | M59: =IF(K59="Sem progresso",0,IF(OR(K59="Não avaliado",K59="Não se aplica",K59=""),"",L59)) -> 0.333 | N59: Não há dados específicos sobre o orçamento climático, mas existe o detalhamento da execução orçamentária e financeira do Município de Belém, com possibilidade de pesquisa por projeto/atividade, por função/subfunção, por natureza de despesa, por fonte e por fundo, sendo disponibilizadas no formato .pdf, mediante o website: https://portaltransparencia.belem.pa.gov.br/despesas/despesas-detalhadas/. Informações a respeito de ações relacionadas às mudanças do clima podem ser acessadas no site Agência Belém, mediante o website: https://agenciabelem.com.br/. Além disso, os processos licitatórios são divulgados na página do site da prefeitura: https://portaltransparencia.belem.pa.gov.br/licitacoes-e-contratos/processos-licitatorios/ | P59: P
A60: 8561 | B60: Financiamento | C60: F2 | D60: Captação de recursos | E60: A | F60: Município | G60: Belém | H60: 1501402 | I60: 45912.512 | J60: Versão de Avaliação 2025 | K60: Estágio inicial | L60: 0.333 | M60: =IF(K60="Sem progresso",0,IF(OR(K60="Não avaliado",K60="Não se aplica",K60=""),"",L60)) -> 0.333 | N60: Não há mapeamento das oportunidades de obtenção de recursos a partir da adesão aos instrumentos da PNMC (ou setoriais) ou de outros planos estaduais, com identificação de quais são mais adequadas para os projetos prioritários. Porém, a prefeitura Municipal de Belém aderiu ao Novo PAC (Programa de Aceleração do Crescimento) visando a obter recursos para execução de programas indiretamente relacionados às mudanças do clima, a exemplo do Programa de Macrodrenagem da Bacia Hidrográfica do Mata Fome (PROMMAF). | P60: P
A61: 8547 | B61: Financiamento | C61: F2 | D61: Captação de recursos | E61: B | F61: Município | G61: Belém | H61: 1501402 | I61: 45912.512 | J61: Versão de Avaliação 2025 | K61: Estágio inicial | L61: 0.333 | M61: =IF(K61="Sem progresso",0,IF(OR(K61="Não avaliado",K61="Não se aplica",K61=""),"",L61)) -> 0.333 | N61: Não há mapeamento das oportunidades de obtenção de financiamento para as ações climáticas, com identificação de quais linhas são mais adequadas para os projetos prioritários, com um planejamento estratégico para acesso a fontes que não sejam do próprio orçamento. Porém, a prefeitura Municipal de Belém acessou a "Linha de financiamento Verde" com o Fundo Financeiro para o Desenvolvimento da Bacia do Prata (FONPLATA) para execução de programas indiretamente relacionados às mudanças do clima, a exemplo do Programa de Macrodrenagem da Bacia Hidrográfica do Mata Fome (PROMMAF). | P61: P
A62: 8566 | B62: Financiamento | C62: F2 | D62: Captação de recursos | E62: C | F62: Município | G62: Belém | H62: 1501402 | I62: 45912.512 | J62: Versão de Avaliação 2025 | K62: Estágio inicial | L62: 0.333 | M62: =IF(K62="Sem progresso",0,IF(OR(K62="Não avaliado",K62="Não se aplica",K62=""),"",L62)) -> 0.333 | N62: A Prefeitura do Município de Belém possui site em que se disponibilizam os instrumentos básicos utilizados na captação de recursos para execução de ações indiretamente relacionadas à política climática, porém, não atualizadas e de difícil acesso, a exemplo do seguinte link: https://segep.belem.pa.gov.br/prommaf/. | P62: P
A63: 8526 | B63: Financiamento | C63: F3 | D63: Mobilização de investimento privado | E63: A | F63: Município | G63: Belém | H63: 1501402 | I63: 45912.512 | J63: Versão de Avaliação 2025 | K63: Estágio inicial | L63: 0.333 | M63: =IF(K63="Sem progresso",0,IF(OR(K63="Não avaliado",K63="Não se aplica",K63=""),"",L63)) -> 0.333 | N63: Não há mapeamento de possíveis oportunidades para incentivar empresas e cidadãos a investirem em ações para mitigação e adaptação das mudanças climáticas. Porém, o Município de Belém oferece isenção do pagamento do Imposto Predial e Territorial Urbano (IPTU) ao proprietário de imóvel cujo ecossistema natural seja preservado ou restaurado no todo ou em parte, e que tenha relevância para o equilíbrio ecológico, atendendo a interesse público e da coletividade, mediante avaliação técnica e autorização do órgão responsável pela política ambiental municipal. | P63: P
A64: 8567 | B64: Financiamento | C64: F3 | D64: Mobilização de investimento privado | E64: B | F64: Município | G64: Belém | H64: 1501402 | I64: 45912.512 | J64: Versão de Avaliação 2025 | K64: Estágio inicial | L64: 0.333 | M64: =IF(K64="Sem progresso",0,IF(OR(K64="Não avaliado",K64="Não se aplica",K64=""),"",L64)) -> 0.333 | N64: Não há dados específicos sobre investimento privados em projetos climáticos, mas existe o detalhamento da execução orçamentária e financeira do Município de Belém, com possibilidade de pesquisa por projeto/atividade, por função/subfunção, por natureza de despesa, por fonte e por fundo, sendo disponibilizadas no formato .pdf, mediante o website: https://portaltransparencia.belem.pa.gov.br/despesas/despesas-detalhadas/. Informações a respeito de ações relacionadas às mudanças do clima podem ser acessadas no site Agência Belém, mediante o website: https://agenciabelem.com.br/. | P64: P
A65: 5471 | B65: Financiamento | C65: F1 | D65: Finanças e gastos públicos | E65: A | F65: Município | G65: Boa Vista | H65: 1400100 | I65: 45888.598 | J65: Versão de Avaliação 2025 | K65: Sem progresso | M65: =IF(K65="Sem progresso",0,IF(OR(K65="Não avaliado",K65="Não se aplica",K65=""),"",L65)) -> 0 | N65: Não há previsão específica no PPA ou leis orçamentárias do município de Boa Vista de ações ou recursos para o enfrentamento das mudanças climáticas e seus impactos. | P65: P
A66: 5472 | B66: Financiamento | C66: F1 | D66: Finanças e gastos públicos | E66: B | F66: Município | G66: Boa Vista | H66: 1400100 | I66: 45888.598 | J66: Versão de Avaliação 2025 | K66: Sem progresso | M66: =IF(K66="Sem progresso",0,IF(OR(K66="Não avaliado",K66="Não se aplica",K66=""),"",L66)) -> 0 | N66: O município de Boa Vista não adota nenhuma metodologia de identificação dos gastos climáticos em seu orçamento. | P66: P
A67: 5460 | B67: Financiamento | C67: F1 | D67: Finanças e gastos públicos | E67: C | F67: Município | G67: Boa Vista | H67: 1400100 | I67: 45888.598 | J67: Versão de Avaliação 2025 | K67: Sem progresso | M67: =IF(K67="Sem progresso",0,IF(OR(K67="Não avaliado",K67="Não se aplica",K67=""),"",L67)) -> 0 | N67: Não existem mecanismos formais no município que estabeleçam critérios de sustentabilidade ou de mitigação/adaptação nas compras e contratações públicas. | P67: P
A68: 5473 | B68: Financiamento | C68: F1 | D68: Finanças e gastos públicos | E68: D | F68: Município | G68: Boa Vista | H68: 1400100 | I68: 45888.598 | J68: Versão de Avaliação 2025 | K68: Sem progresso | M68: =IF(K68="Sem progresso",0,IF(OR(K68="Não avaliado",K68="Não se aplica",K68=""),"",L68)) -> 0 | N68: O município de Boa Vista não possui mecanismos de transparência ativa que forneçam informações específicas sobre orçamento e gasto público climático. | P68: P
A69: 5474 | B69: Financiamento | C69: F2 | D69: Captação de recursos | E69: A | F69: Município | G69: Boa Vista | H69: 1400100 | I69: 45888.598 | J69: Versão de Avaliação 2025 | K69: Sem progresso | M69: =IF(K69="Sem progresso",0,IF(OR(K69="Não avaliado",K69="Não se aplica",K69=""),"",L69)) -> 0 | N69: Não existem mecanismos que viabilizem a adesão do município a políticas/programas federais e/ou estaduais. | P69: P
A70: 5475 | B70: Financiamento | C70: F2 | D70: Captação de recursos | E70: B | F70: Município | G70: Boa Vista | H70: 1400100 | I70: 45888.598 | J70: Versão de Avaliação 2025 | K70: Sem progresso | M70: =IF(K70="Sem progresso",0,IF(OR(K70="Não avaliado",K70="Não se aplica",K70=""),"",L70)) -> 0 | N70: Não existem no município mecanismos que viabilizam a identificação de oportunidades para acesso a fontes de recursos financeiros para projetos específicos de do enfrentamento da mudança do clima. | P70: P
A71: 5476 | B71: Financiamento | C71: F2 | D71: Captação de recursos | E71: C | F71: Município | G71: Boa Vista | H71: 1400100 | I71: 45888.598 | J71: Versão de Avaliação 2025 | K71: Sem progresso | M71: =IF(K71="Sem progresso",0,IF(OR(K71="Não avaliado",K71="Não se aplica",K71=""),"",L71)) -> 0 | N71: Não existem no município mecanismos que viabilizam a identificação de oportunidades para acesso a fontes de recursos financeiros para projetos específicos de do enfrentamento da mudança do clima. | P71: P
A72: 5481 | B72: Financiamento | C72: F3 | D72: Mobilização de investimento privado | E72: A | F72: Município | G72: Boa Vista | H72: 1400100 | I72: 45888.598 | J72: Versão de Avaliação 2025 | K72: Sem progresso | M72: =IF(K72="Sem progresso",0,IF(OR(K72="Não avaliado",K72="Não se aplica",K72=""),"",L72)) -> 0 | N72: O município de Boa Vista não possui instrumento legal/mecanismo que fomente a mobilização de recursos privados em ações que contribuem para o alcance dos objetivos climáticos. | P72: P
A73: 5477 | B73: Financiamento | C73: F3 | D73: Mobilização de investimento privado | E73: B | F73: Município | G73: Boa Vista | H73: 1400100 | I73: 45888.598 | J73: Versão de Avaliação 2025 | K73: Sem progresso | M73: =IF(K73="Sem progresso",0,IF(OR(K73="Não avaliado",K73="Não se aplica",K73=""),"",L73)) -> 0 | N73: O município de Boa Vista não possui instrumento que estimule a mobilização de recursos privados em ações para o alcance dos objetivos climáticos. | P73: P
A74: 7064 | B74: Financiamento | C74: F1 | D74: Finanças e gastos públicos | E74: A | F74: Município | G74: Campo Grande | H74: 5002704 | I74: 45899.601 | J74: Versão de Avaliação 2025 | K74: Estágio inicial | L74: 0.333 | M74: =IF(K74="Sem progresso",0,IF(OR(K74="Não avaliado",K74="Não se aplica",K74=""),"",L74)) -> 0.333 | N74: O PPA 2022-2025 e a LDO2025 incluem a sustentabilidade ambiental e o desenvolvimento sustentável como diretrizes e prioridades. A LOA 2025 na Ação 4031 - Planejamento Ambiental reserva alocação de recursos que está diretamente alinhada a uma iniciativa do PPA 2022-2025 (Iniciativa 14 - Elaborar Plano de Ações Climáticas). As diretrizes do PPA e da LDO mencionam sustentabilidade e meio ambiente. | P74: P
A75: 7065 | B75: Financiamento | C75: F1 | D75: Finanças e gastos públicos | E75: B | F75: Município | G75: Campo Grande | H75: 5002704 | I75: 45899.601 | J75: Versão de Avaliação 2025 | K75: Sem progresso | M75: =IF(K75="Sem progresso",0,IF(OR(K75="Não avaliado",K75="Não se aplica",K75=""),"",L75)) -> 0 | N75: O município ainda não possui uma taxonomia específica ou sistema de marcação de despesas voltadas exclusivamente ao clima. Está em estudo a criação de categorias que permitam rastrear gastos climáticos diretos e indiretos, como parte da estruturação do Plano de Descarbonização. | P75: P
A76: 7077 | B76: Financiamento | C76: F1 | D76: Finanças e gastos públicos | E76: C | F76: Município | G76: Campo Grande | H76: 5002704 | I76: 45899.601 | J76: Versão de Avaliação 2025 | K76: Estágio inicial | L76: 0.333 | M76: =IF(K76="Sem progresso",0,IF(OR(K76="Não avaliado",K76="Não se aplica",K76=""),"",L76)) -> 0.333 | N76: De acordo com o Manual de compras públicas governamentais do município, há uma indicação de mecanismos para a inclusão de critérios de sustentabilidade de forma geral. Não há evidências claras e específicas de mecanismos que promovam a adoção de critérios relacionados à redução de GEE e adaptação à mudança do clima. Não há evidências de mecanismos para impulsionar a construção de capacidades técnicas específicas para critérios climáticos. | P76: P
A77: 7083 | B77: Financiamento | C77: F1 | D77: Finanças e gastos públicos | E77: D | F77: Município | G77: Campo Grande | H77: 5002704 | I77: 45899.601 | J77: Versão de Avaliação 2025 | K77: Sem progresso | M77: =IF(K77="Sem progresso",0,IF(OR(K77="Não avaliado",K77="Não se aplica",K77=""),"",L77)) -> 0 | N77: Segundo a equipe da prefeitura, os projetos relacionados ao Plano de Descarbonização SERÃO divulgados com maior detalhamento após sua aprovação. Não há dados atualizados e acessíveis em formato de dados abertos e linguagem simples sobre o financiamento público das políticas climáticas. | P77: P
A78: 7086 | B78: Financiamento | C78: F2 | D78: Captação de recursos | E78: A | F78: Município | G78: Campo Grande | H78: 5002704 | I78: 45899.601 | J78: Versão de Avaliação 2025 | K78: Estágio intermediário | L78: 0.666 | M78: =IF(K78="Sem progresso",0,IF(OR(K78="Não avaliado",K78="Não se aplica",K78=""),"",L78)) -> 0.666 | N78: Campo Grande integra o Programa "Cidades Modelo Verdes Resilientes" do Governo Federal, que fornecerá suporte técnico para desenvolver ações climáticas de mitigação e adaptação. Também firmou o Termo de Compromisso da Agenda Local do Roadmap Território Carbono Neutro, coordenado pela Semadesc e Sebrae/MS, visando avaliar a maturidade climática e apoiar a implementação de ações. Tem Termo de Cooperação com a concessionária Águas Guariroba para o Programa "Córrego Limpo, Cidade Viva" é outro exemplo de parceria. | P78: P
A79: 7155 | B79: Financiamento | C79: F2 | D79: Captação de recursos | E79: B | F79: Município | G79: Campo Grande | H79: 5002704 | I79: 45899.601 | J79: Versão de Avaliação 2025 | K79: Estágio intermediário | L79: 0.666 | M79: =IF(K79="Sem progresso",0,IF(OR(K79="Não avaliado",K79="Não se aplica",K79=""),"",L79)) -> 0.666 | N79: Há evidências de mapeamento e planejamento estratégico para acesso a fontes de financiamento externas para projetos específicos. E tem capacidade técnica para elaboração de projetos competitivos é evidente, seja pela contratação de consultoria especializada ou pelo desenvolvimento interno e diagnóstico positivo de maturidade nos documentos suporte e na equipe da Agência Municipal de Meio Ambiente e Planejamento Urbano.Por fim, o município conseguiu captar recursos (cooperação técnica e financiamento) de uma das fontes exemplificadas (BID), e está inserido em outros programas que fornecem suporte para o desenvolvimento de ações. | P79: P
A80: 7183 | B80: Financiamento | C80: F2 | D80: Captação de recursos | E80: C | F80: Município | G80: Campo Grande | H80: 5002704 | I80: 45899.601 | J80: Versão de Avaliação 2025 | K80: Sem progresso | M80: =IF(K80="Sem progresso",0,IF(OR(K80="Não avaliado",K80="Não se aplica",K80=""),"",L80)) -> 0 | N80: Atualmente NÃO há ações para a captação de recursos para execução de ações de política climática COM MONITORAMENTO de modo contínuo e/ou regular (ao menos uma vez ao ano) pelo município. Não há plataformas específicas (mecanismos) que apresentem dados sobre a captação de recursos para execução de ações de política climática. Segundo a prefeitura há previsão de criar um painel digital de acompanhamento das metas climáticas com origem de recursos e progresso das ações. | P80: P
A81: 7204 | B81: Financiamento | C81: F3 | D81: Mobilização de investimento privado | E81: A | F81: Município | G81: Campo Grande | H81: 5002704 | I81: 45899.601 | J81: Versão de Avaliação 2025 | K81: Estágio intermediário | L81: 0.666 | M81: =IF(K81="Sem progresso",0,IF(OR(K81="Não avaliado",K81="Não se aplica",K81=""),"",L81)) -> 0.666 | N81: O município oferece benefício tributário, consistente na redução do Imposto Predial e Territorial Urbano - IPTU e ISS - Imposto sobre Serviços de qualquer natureza, às pessoas físicas e jurídicas proprietárias de imóveis residenciais e comerciais que adotem uma das medidas que estimulem a proteção, preservação e recuperação do meio ambiente. Essas ações buscam Melhorar o perfil de risco-retorno de projetos específicos e contribuir para convencer os financiadores privados a investirem em ações para mitigação e adaptação das mudanças climáticas. | P81: P
A82: 7211 | B82: Financiamento | C82: F3 | D82: Mobilização de investimento privado | E82: B | F82: Município | G82: Campo Grande | H82: 5002704 | I82: 45899.601 | J82: Versão de Avaliação 2025 | K82: Sem progresso | M82: =IF(K82="Sem progresso",0,IF(OR(K82="Não avaliado",K82="Não se aplica",K82=""),"",L82)) -> 0 | N82: Não há nenhum monitoramento específico sobre o programa de incentivo promovido pelo município. | P82: P
A83: 7141 | B83: Financiamento | C83: F1 | D83: Finanças e gastos públicos | E83: A | F83: Estado | G83: Ceará | H83: 23 | I83: 45918.555 | J83: Versão de Avaliação 2025 | K83: Estágio intermediário | L83: 0.666 | M83: =IF(K83="Sem progresso",0,IF(OR(K83="Não avaliado",K83="Não se aplica",K83=""),"",L83)) -> 0.666 | N83: A classificação como Estágio Intermediário decorre da análise dos seguintes elementos: 1) O PPA incorpora diretrizes climáticas, atendendo ao Atributo 1, porém sem detalhamento de mecanismos de implementação intersetorial 2) Há alocação orçamentária específica para clima em 2024 e 2025 (Atributo 2), mas com limitações quantitativas e ausência de previsão de aumento progressivo 3) Identificou-se alinhamento parcial entre recursos e políticas climáticas (Atributo 3): 70% das ações orçadas relacionam-se a planos existentes, mas 30% carecem de vinculação a instrumentos normativos ou prioridades territoriais. Conforme o manual, o estágio intermediário aplica-se quando há avanços estruturais, mas persistem lacunas operacionais. No caso, a falta de integração entre orçamento e metas setoriais, somada à baixa proporção de recursos frente aos desafios climáticos locais, impede a classificação como avançado. Recomenda-se a revisão do PPA para incluir indicadores de eficiência alocativa e ampliar o diálogo com setores-chave (agricultura, energia). | P83: P
A84: 7161 | B84: Financiamento | C84: F1 | D84: Finanças e gastos públicos | E84: B | F84: Estado | G84: Ceará | H84: 23 | I84: 45918.555 | J84: Versão de Avaliação 2025 | K84: Sem progresso | M84: =IF(K84="Sem progresso",0,IF(OR(K84="Não avaliado",K84="Não se aplica",K84=""),"",L84)) -> 0 | N84: A análise identificou ausência de documentação comprobatória quanto à implementação de metodologia para rastreamento de gastos climáticos, requisito mínimo para o estágio inicial. A não diferenciação de ações climáticas no orçamento - corroborada pela inexistência de códigos específicos ou relatórios setoriais - impossibilita verificar alocação efetiva de recursos. | P84: P
A85: 7162 | B85: Financiamento | C85: F1 | D85: Finanças e gastos públicos | E85: C | F85: Estado | G85: Ceará | H85: 23 | I85: 45918.555 | J85: Versão de Avaliação 2025 | K85: Estágio inicial | L85: 0.333 | M85: =IF(K85="Sem progresso",0,IF(OR(K85="Não avaliado",K85="Não se aplica",K85=""),"",L85)) -> 0.333 | N85: A análise revela que o ente auditado dispõe de mecanismos incipientes para incorporação de critérios sustentáveis e climáticos em contratações, como normativos pontuais e capacitação esporádica. Contudo, falta padronização de cláusulas obrigatórias em todos os processos, diretrizes claras para redução de emissões e monitoramento contínuo das capacitações. A ausência de sistemas integrados para verificação de conformidade e a limitação na abrangência dos critérios indicam fragilidades na implementação, caracterizando estágio inicial de maturidade. | P85: P
A86: 7163 | B86: Financiamento | C86: F1 | D86: Finanças e gastos públicos | E86: D | F86: Estado | G86: Ceará | H86: 23 | I86: 45918.555 | J86: Versão de Avaliação 2025 | K86: Estágio inicial | L86: 0.333 | M86: =IF(K86="Sem progresso",0,IF(OR(K86="Não avaliado",K86="Não se aplica",K86=""),"",L86)) -> 0.333 | N86: A análise evidenciou esforços incipientes de transparência, com a produção periódica de relatórios institucionais. Contudo, os critérios de dados abertos e transparência ativa não foram integralmente atendidos: a) Fragilidades críticas: Ausência de padronização em formatos reutilizáveis e carência de mecanismos que permitam o cruzamento de dados por terceiros (ex.: valores executados por ação climática). b) Barreira de acesso: Informações técnicas não são traduzidas para linguagem cidadã, limitando o controle social. c) Omissão em emergências: Lacuna na divulgação de contratos emergenciais pós-desastres, fator essencial para avaliar a eficácia de respostas rápidas. | P86: P
A87: 7152 | B87: Financiamento | C87: F2 | D87: Captação de recursos | E87: A | F87: Estado | G87: Ceará | H87: 23 | I87: 45918.555 | J87: Versão de Avaliação 2025 | K87: Estágio inicial | L87: 0.333 | M87: =IF(K87="Sem progresso",0,IF(OR(K87="Não avaliado",K87="Não se aplica",K87=""),"",L87)) -> 0.333 | N87: Mapeamento não é sistêmico: Embora o estado utilize programas federais, não há evidências de um diagnóstico que priorize ou articule essas ferramentas com suas metas climáticas locais (ex.: plano estadual de adaptação não citado) Implementação é setorial: A participação no MCMV e ABC+ não inclui critérios climáticos explícitos na execução (ex.: habitações do MCMV não têm certificação de eficiência energética) Capacidade técnica limitada: Não há menção a unidades especializadas ou sistemas de monitoramento de resultados climáticos (ex.: redução de emissões gerada pelo ABC+ não foi quantificada). | P87: P
A88: 7153 | B88: Financiamento | C88: F2 | D88: Captação de recursos | E88: B | F88: Estado | G88: Ceará | H88: 23 | I88: 45918.555 | J88: Versão de Avaliação 2025 | K88: Estágio inicial | L88: 0.333 | M88: =IF(K88="Sem progresso",0,IF(OR(K88="Não avaliado",K88="Não se aplica",K88=""),"",L88)) -> 0.333 | N88: A avaliação identificou a existência inicial de mecanismos de identificação de fontes de recursos, conforme evidenciado pelo mapeamento parcial de linhas de financiamento climático. Entretanto, a ausência de planejamento estratégico integrado e a inadequação dos projetos às exigências técnicas dos financiadores (comprovada pela inexistência de aprovações) limitam a eficácia da captação. A capacidade técnica insipiente da equipe foi verificada através da análise de propostas genéricas, sem aderência a critérios específicos de editais internacionais ou REDD+. A inexistência de recursos efetivamente captados - mesmo identificando-se tentativas de submissão a programas federais - reforça a lacuna operacional. Conclui-se que os mecanismos existentes atendem parcialmente aos atributos 1 a 3, caracterizando um estágio incipiente de desenvolvimento institucional para acesso a fontes alternativas. Esse cenário demanda ações corretivas prioritárias para estruturação de fluxos de trabalho especializados e fortalecimento da governança financeira climática. | P88: P
A89: 7154 | B89: Financiamento | C89: F2 | D89: Captação de recursos | E89: C | F89: Estado | G89: Ceará | H89: 23 | I89: 45918.555 | J89: Versão de Avaliação 2025 | K89: Estágio inicial | L89: 0.333 | M89: =IF(K89="Sem progresso",0,IF(OR(K89="Não avaliado",K89="Não se aplica",K89=""),"",L89)) -> 0.333 | N89: A reanálise demonstra que apenas o atributo 1 é atendido minimamente, porém sem regularidade comprovada (ações pontuais - monitoramento contínuo). A ausência de plataforma unificada ou relatórios com periodicidade definida inviabiliza o atendimento ao atributo 2, caracterizando mera produção ocasional de documentos. Quanto à transparência ativa (atributo 3), a disponibilização de dados em formatos não reutilizáveis e sem metadados descaracteriza o acesso aberto. | P89: P
A90: 7381 | B90: Financiamento | C90: F3 | D90: Mobilização de investimento privado | E90: A | F90: Estado | G90: Ceará | H90: 23 | I90: 45918.555 | J90: Versão de Avaliação 2025 | K90: Estágio avançado | L90: 1 | M90: =IF(K90="Sem progresso",0,IF(OR(K90="Não avaliado",K90="Não se aplica",K90=""),"",L90)) -> 1 | N90: Existência de instrumentos normativos ativos (ex: condicionalidade de benefícios fiscais a critérios ESG - Art. 3º, §3º da Lei 19.139) Mobilização indireta via regulação (ex: ajustes em procedimentos licitatórios para viabilizar parcerias público-privadas - Art. 10 da Lei 19.139) Articulação intersetorial comprovada na estrutura do Conselho de Governança (Lei 18.459, Art. 6º), que inclui entes privados e academia. | P90: P
A91: 7363 | B91: Financiamento | C91: F3 | D91: Mobilização de investimento privado | E91: B | F91: Estado | G91: Ceará | H91: 23 | I91: 45918.555 | J91: Versão de Avaliação 2025 | K91: Estágio inicial | L91: 0.333 | M91: =IF(K91="Sem progresso",0,IF(OR(K91="Não avaliado",K91="Não se aplica",K91=""),"",L91)) -> 0.333 | N91: A análise das evidências indica ajuste na classificação: 1) Monitoramento regular: Existem mecanismos formais (relatórios anuais previstos na Lei 18.459/2023, Art. 5º, IV) 2) Divulgação insuficiente: Falha no atributo 2: As informações são restritas a relatórios técnicos sem plataforma específica (ex: portal climático) ou atualização contínua Falha no atributo 3: Dados não estão em formato aberto/desagregado (Lei 19.139/2024 não prevê APIs, CSV ou mecanismos de busca avançada) Ausência de comprovação sobre linguagem acessível ao cidadão (ex: resumos executivos simplificados). Classificação para Estágio Inicial justifica-se porque: Apenas o atributo 1 foi integralmente atendido (monitoramento anual) Atributos 2 e 3 não possuem evidências de implementação (ex: sistemas digitais de transparência ativa, dados auditáveis em tempo real). Apenas o atributo 1 foi integralmente atendido (monitoramento anual) Atributos 2 e 3 não possuem evidências de implementação (ex: sistemas digitais de transparência ativa, dados auditáveis em tempo real). | P91: P
A92: 4927 | B92: Financiamento | C92: F1 | D92: Finanças e gastos públicos | E92: A | F92: Município | G92: Cuiabá | H92: 5103403 | I92: 45905.603 | J92: Versão de Avaliação 2025 | K92: Sem progresso | M92: =IF(K92="Sem progresso",0,IF(OR(K92="Não avaliado",K92="Não se aplica",K92=""),"",L92)) -> 0 | N92: "A situação avaliada enquadra-se na classificação ""Sem Progresso"", uma vez que não há atendimento integral a nenhum dos três atributos exigidos. Apesar da existência de recursos ambientais no planejamento municipal, a ausência de diretrizes específicas voltadas à agenda climática no Plano Plurianual (PPA) e a inexistência de políticas climáticas formalmente instituídas impedem uma classificação mais elevada. Principais lacunas identificadas: Ausência de diretrizes climáticas nas leis orçamentárias Principais lacunas identificadas: Ausência de diretrizes climáticas nas leis orçamentárias
A93: 5021 | B93: Financiamento | C93: F1 | D93: Finanças e gastos públicos | E93: B | F93: Município | G93: Cuiabá | H93: 5103403 | I93: 45905.603 | J93: Versão de Avaliação 2025 | K93: Sem progresso | M93: =IF(K93="Sem progresso",0,IF(OR(K93="Não avaliado",K93="Não se aplica",K93=""),"",L93)) -> 0 | N93: A avaliação do Item B - Rastreamento das Despesas Climáticas - concluiu que o município de Cuiabá não atende a nenhum dos quatro atributos exigidos, resultando na classificação "Sem Progresso". O atributo 1, que exige a existência de metodologia formal para identificar gastos climáticos, não foi atendido, o que compromete o atendimento dos demais critérios. Atributo 1 (Metodologia formal): não atendido. Atributo 2 (Códigos/marcações orçamentárias): não atendido. Atributo 3 (Rastreamento de gastos indiretos): não atendido. Atributo 4 (Identificação de gastos negativos): não atendido. A ausência de metodologia formal inviabiliza a estruturação de um sistema eficaz de rastreio, conforme os parâmetros da metodologia adotada. Embora o município possua infraestrutura orçamentária robusta, como o uso do SIAFIC, portal de transparência estruturado e contas regularmente aprovadas pelo TCE-MT, não há qualquer evidência de esforços voltados à marcação ou rastreamento de despesas climáticas. Essa lacuna se destaca negativamente, sobretudo considerando a relevância ambiental de Cuiabá no contexto do Pantanal e Cerrado. Pontos positivos incluem a modernidade da gestão orçamentária e o cumprimento de requisitos de transparência e controle externo. Contudo, permanecem lacunas críticas, como a total ausência de capacidades específicas para rastreamento climático e a inexistência de um Plano Municipal de Mudanças Climáticas. | P93: P
A94: 5041 | B94: Financiamento | C94: F1 | D94: Finanças e gastos públicos | E94: C | F94: Município | G94: Cuiabá | H94: 5103403 | I94: 45905.603 | J94: Versão de Avaliação 2025 | K94: Sem progresso | M94: =IF(K94="Sem progresso",0,IF(OR(K94="Não avaliado",K94="Não se aplica",K94=""),"",L94)) -> 0 | N94: Não existem mecanismos que promovam a adoção de critérios e práticas de sustentabilidade ou de mitigação/adaptação nas compras e contratações públicas | P94: P
A95: 5022 | B95: Financiamento | C95: F1 | D95: Finanças e gastos públicos | E95: D | F95: Município | G95: Cuiabá | H95: 5103403 | I95: 45905.603 | J95: Versão de Avaliação 2025 | K95: Sem progresso | M95: =IF(K95="Sem progresso",0,IF(OR(K95="Não avaliado",K95="Não se aplica",K95=""),"",L95)) -> 0 | N95: Embora o município possua mecanismos gerais de transparência, não atende aos requisitos específicos para monitoramento de políticas climáticas. A transparência genérica não substitui a necessidade de sistemas dedicados exclusivamente ao acompanhamento de orçamentos e gastos climáticos. Considerando a ausência completa de mecanismos específicos para transparência climática em todos os quatro atributos avaliados, classifica-se como "Sem progresso". | P95: P
A96: 5042 | B96: Financiamento | C96: F2 | D96: Captação de recursos | E96: A | F96: Município | G96: Cuiabá | H96: 5103403 | I96: 45905.603 | J96: Versão de Avaliação 2025 | K96: Sem progresso | M96: =IF(K96="Sem progresso",0,IF(OR(K96="Não avaliado",K96="Não se aplica",K96=""),"",L96)) -> 0 | N96: Não existem mecanismos nem capacidades internas que viabilizem a adesão do ente federativo a políticas ou programas federais e/ou estaduais" relacionados a mudanças climáticas. | P96: P
A97: 5181 | B97: Financiamento | C97: F2 | D97: Captação de recursos | E97: B | F97: Município | G97: Cuiabá | H97: 5103403 | I97: 45905.603 | J97: Versão de Avaliação 2025 | K97: Estágio inicial | L97: 0.333 | M97: =IF(K97="Sem progresso",0,IF(OR(K97="Não avaliado",K97="Não se aplica",K97=""),"",L97)) -> 0.333 | N97: Cuiabá foi classificada no ESTÁGIO INICIAL para o Item B por atender parcialmente apenas um dos três critérios avaliados. CRITÉRIO 1 - MAPEAMENTO DE OPORTUNIDADES: NÃO ATENDE. Não foram encontradas evidências de mecanismos sistemáticos para identificação de linhas de financiamento climático. A análise do documento F2-B(2).pdf (860 páginas) não apresentou referências a fundos como REDD+, GEF ou GCF. CRITÉRIO 2 - CAPACIDADE TÉCNICA: PARCIALMENTE ATENDE. A SMADES possui estrutura institucional estabelecida pela Lei Complementar 146/2007 (páginas 1-2), com competências para licenciamento ambiental e celebração de convênios. O documento F2-B(2).pdf confirma participação da SMADES no Conselho do Plano Diretor (página 835). Contudo, não há evidências de equipe especializada em projetos para fundos climáticos internacionais. CRITÉRIO 3 - CAPTAÇÃO EFETIVA: NÃO ATENDE PARA MUDANÇAS CLIMÁTICAS. Embora o município tenha histórico de captação de recursos do BNDES para infraestrutura geral (páginas 589-590 do F2-B(2).pdf), não foram encontradas evidências de captação específica para projetos de mudanças climáticas. O Ementário da Legislação Municipal 2011 documenta financiamentos gerais, mas não climáticos. A classificação reflete a ausência de mecanismos específicos para mudanças climáticas, mantendo Cuiabá no estágio inicial. | P97: P
A98: 5182 | B98: Financiamento | C98: F2 | D98: Captação de recursos | E98: C | F98: Município | G98: Cuiabá | H98: 5103403 | I98: 45905.603 | J98: Versão de Avaliação 2025 | K98: Sem progresso | M98: =IF(K98="Sem progresso",0,IF(OR(K98="Não avaliado",K98="Não se aplica",K98=""),"",L98)) -> 0 | N98: Cuiabá foi classificada em SEM PROGRESSO para o Item F2-C devido ao não atendimento dos critérios de monitoramento e transparência de políticas climáticas. ATRIBUTO 1 (Monitoramento Regular): NÃO ATENDE. O Portal da SMADES (https://www.cuiaba.mt.gov.br/secretarias/meio-ambiente-e-desenvolvimento-urbano/residuos-solidos) disponibiliza relatórios de monitoramento de resíduos sólidos de 2010-2012, o que demonstra que esses documentos estão desatualizados. Destaca-se também que esses relatórios tratam da gestão de resíduos sólidos, não do monitoramento da "captação de recursos para execução de ações de política climática". ATRIBUTO 2 (Transparência Ativa): NÃO ATENDE. O Portal de Transparência (http://transparencia.cuiaba.mt.gov.br/) possui estrutura adequada, mas carece de seção específica para recursos climáticos. O Portal da SMADES disponibiliza documentos técnicos, porém sem foco em captação de recursos climáticos. ATRIBUTO 3 (Acessibilidade): NÃO ATENDE. Dados disponíveis apenas em PDF, não reutilizáveis. Ausência de portal municipal de dados abertos e APIs, conforme verificado nos portais consultados. A classificação em SEM PROGRESSO reflete mecanismos básicos de transparência e capacidade técnica demonstrada, mas com limitações na divulgação de dados específicos sobre políticas climáticas. | P98: P
A99: 5183 | B99: Financiamento | C99: F3 | D99: Mobilização de investimento privado | E99: A | F99: Município | G99: Cuiabá | H99: 5103403 | I99: 45905.603 | J99: Versão de Avaliação 2025 | K99: Estágio avançado | L99: 1 | M99: =IF(K99="Sem progresso",0,IF(OR(K99="Não avaliado",K99="Não se aplica",K99=""),"",L99)) -> 1 | N99: Cuiabá foi classificada no "Estágio Avançado" quanto à mobilização de financiamento climático privado, com base nas seguintes evidências: Mecanismos estruturados: A Lei Complementar 515/2022 institui o IPTU Sustentável, com descontos de até 25% para imóveis que adotem 9 tecnologias sustentáveis. A Lei Complementar 321/2013 criou o Fundo Municipal de Meio Ambiente (FMMA), com 13 fontes de recursos voltadas ao financiamento de projetos governamentais e não governamentais. Mobilização efetiva em 2024-2025: Foram mobilizados recursos privados relevantes, como os R$ 973.639,00 destinados pela Iguá Saneamento a projetos socioambientais em 2025. O IPTU Sustentável beneficiou mais de 1.100 munícipes, e a Parceria Público-Privada do Mercado Municipal movimentou R$ 125 milhões. Cuiabá alcançou o 2º lugar nacional em potência instalada de energia solar, com 296 MW. Adequação ao contexto local: Os incentivos são compatíveis com as características climáticas da região, como a valorização da captação de águas pluviais e o uso de energia solar, aproveitando a alta irradiação da cidade. A presença de mecanismos estruturados e a mobilização comprovada de recursos demonstram que o ente federativo possui mecanismos e estruturas e mobilizou recursos privados em ações que contribuem para o alcance dos objetivos climáticos (nos exercícios de 2024-2025), o que justifica a classificação no Estágio Avançado. | P99: P
A100: 5184 | B100: Financiamento | C100: F3 | D100: Mobilização de investimento privado | E100: B | F100: Município | G100: Cuiabá | H100: 5103403 | I100: 45905.603 | J100: Versão de Avaliação 2025 | K100: Sem progresso | M100: =IF(K100="Sem progresso",0,IF(OR(K100="Não avaliado",K100="Não se aplica",K100=""),"",L100)) -> 0 | N100: Cuiabá foi classificada como "Sem Progresso" no item F3-B por não atender a nenhum dos três critérios estabelecidos. Primeiro, não há evidências de monitoramento contínuo e regular das ações de mobilização de recursos privados para ação climática. A análise do Portal de Transparência Municipal, site da SMADESS e Gazeta Municipal não identificou relatórios anuais ou sistemas de acompanhamento específicos. Segundo inexistem mecanismos de transparência ativa com dados atualizados. O Índice de Dados Abertos para Cidades 2023 atribuiu pontuação 0 (opaco) para Cuiabá na dimensão Meio Ambiente, evidenciando ausência de sistemas, dashboards ou plataformas dedicadas à divulgação de informações sobre recursos privados climáticos. Terceiro as informações não estão estruturadas para consulta pública. Os dados encontram-se fragmentados em diferentes portais, sem desagregação específica sobre mobilização de recursos privados, linguagem técnica inacessível e ausência de ferramentas que permitam auditoria cidadã. Esta classificação contrasta com a avaliação anterior, onde Cuiabá demonstrou possuir mecanismos estruturados de mobilização (FMMA, IPTU Sustentável, PPPs), mas falha completamente no monitoramento e transparência dessas ações, comprometendo o controle social e a prestação de contas à população. | P100: P
...
